{
  "_ui": {
    "nodes": {
      "ebb0892f-b657-4094-a934-f29d006f11c7": {
        "config": {
          "cases": {},
          "operand": {
            "id": "next_tip_main",
            "name": "next tip main",
            "type": "field"
          }
        },
        "position": {
          "left": 460,
          "top": 20
        },
        "type": "split_by_contact_field"
      },
      "236c22cb-179c-4775-8547-53a5788d4c3d": {
        "type": "split_by_contact_field",
        "position": {
          "left": 720,
          "top": 80
        },
        "config": {
          "operand": {
            "id": "get_ipv_content",
            "type": "field",
            "name": "get ipv content"
          },
          "cases": {}
        }
      },
      "286d0c22-5644-4d98-9654-8a4eee868644": {
        "config": {},
        "position": {
          "left": 1120,
          "top": 120
        },
        "type": "split_by_subflow"
      },
      "41e98aa6-a4bb-4cf1-b21c-c7ddb582e228": {
        "config": {},
        "position": {
          "left": 20,
          "top": 160
        },
        "type": "split_by_subflow"
      },
      "2edc04f6-03f7-46ff-a68c-36d22a40a9c4": {
        "config": {
          "cases": {},
          "operand": {
            "id": "age_group_for_tips",
            "name": "age group for tips",
            "type": "field"
          }
        },
        "position": {
          "left": 260,
          "top": 180
        },
        "type": "split_by_contact_field"
      },
      "96a9ecfc-2b1c-48ce-b441-8df70165d5a6": {
        "config": {},
        "position": {
          "left": 500,
          "top": 200
        },
        "type": "split_by_subflow"
      },
      "8fdd3f12-cb40-442e-b0b7-41bd7ca6e53c": {
        "config": {},
        "position": {
          "left": 940,
          "top": 260
        },
        "type": "split_by_subflow"
      },
      "61ffef4e-1fba-4c6a-b24b-9db7ddd5ddd6": {
        "type": "split_by_subflow",
        "position": {
          "left": 720,
          "top": 280
        },
        "config": {}
      },
      "4c10cd29-35de-4e82-bfd8-7af1f44c5257": {
        "config": {},
        "position": {
          "left": 220,
          "top": 320
        },
        "type": "split_by_subflow"
      },
      "d0bc8187-3a70-409b-b12b-a1abe9ac76af": {
        "position": {
          "left": 500,
          "top": 440
        },
        "type": "execute_actions"
      },
      "480a1258-2f9d-4401-acf2-e1085ba45c21": {
        "config": {
          "cases": {},
          "operand": {
            "id": "age_group_for_tips",
            "name": "age group for tips",
            "type": "field"
          }
        },
        "position": {
          "left": 40,
          "top": 460
        },
        "type": "split_by_contact_field"
      },
      "8329a0e5-97a6-4e9a-ad7e-fa173cc0d9a2": {
        "config": {},
        "position": {
          "left": 260,
          "top": 480
        },
        "type": "split_by_subflow"
      },
      "846d24dd-f48f-417b-800c-8a35c4b149ef": {
        "position": {
          "left": 500,
          "top": 560
        },
        "type": "execute_actions"
      },
      "fdfa88f1-b1f8-4cb3-9733-3fea1fa83e8e": {
        "config": {},
        "position": {
          "left": 240,
          "top": 620
        },
        "type": "split_by_subflow"
      },
      "49ffd29f-3b40-44e7-a94f-24414ad40856": {
        "config": {},
        "position": {
          "left": 20,
          "top": 720
        },
        "type": "split_by_subflow"
      },
      "18520cad-e755-46da-b872-f412e1528904": {
        "config": {
          "cases": {},
          "operand": {
            "id": "age_group_for_tips",
            "name": "age group for tips",
            "type": "field"
          }
        },
        "position": {
          "left": 1120,
          "top": 740
        },
        "type": "split_by_contact_field"
      },
      "dd83c325-2c09-4e6c-9934-3f2a999a6c08": {
        "type": "split_by_contact_field",
        "position": {
          "left": 540,
          "top": 760
        },
        "config": {
          "operand": {
            "id": "next_tip_main",
            "type": "field",
            "name": "next tip main"
          },
          "cases": {}
        }
      },
      "9eeea984-02e4-4d02-9ec9-80e25e5d4f7c": {
        "config": {},
        "position": {
          "left": 980,
          "top": 860
        },
        "type": "split_by_subflow"
      },
      "7b720b86-12ef-4692-95f0-025a9ba60996": {
        "config": {},
        "position": {
          "left": 1240,
          "top": 860
        },
        "type": "split_by_subflow"
      },
      "3ec246fe-7040-4f45-b292-3113a64de0bc": {
        "config": {
          "cases": {},
          "operand": {
            "id": "age_group_for_tips",
            "name": "age group for tips",
            "type": "field"
          }
        },
        "position": {
          "left": 320,
          "top": 880
        },
        "type": "split_by_contact_field"
      },
      "ff94d097-0df5-426f-982f-0d6d812d8937": {
        "config": {
          "cases": {},
          "operand": {
            "id": "age_group_for_tips",
            "name": "age group for tips",
            "type": "field"
          }
        },
        "position": {
          "left": 600,
          "top": 900
        },
        "type": "split_by_contact_field"
      },
      "c89ae386-5859-41d1-973d-81885d983b1a": {
        "config": {
          "cases": {},
          "operand": {
            "id": "age_group_for_tips",
            "name": "age group for tips",
            "type": "field"
          }
        },
        "position": {
          "left": 40,
          "top": 920
        },
        "type": "split_by_contact_field"
      },
      "a23adf12-69fe-4b9b-838c-a924e1848c49": {
        "config": {},
        "position": {
          "left": 280,
          "top": 1000
        },
        "type": "split_by_subflow"
      },
      "f6bbe8c7-b30f-4008-a9a7-ebc11c228046": {
        "config": {},
        "position": {
          "left": 40,
          "top": 1040
        },
        "type": "split_by_subflow"
      },
      "2ab85e63-4e95-4dd8-bad3-e6aa4c76e81c": {
        "config": {},
        "position": {
          "left": 540,
          "top": 1060
        },
        "type": "split_by_subflow"
      },
      "d22d7db9-9537-4617-9099-4a12eaa62566": {
        "config": {
          "cases": {},
          "operand": {
            "id": "age_group_for_tips",
            "name": "age group for tips",
            "type": "field"
          }
        },
        "position": {
          "left": 880,
          "top": 1120
        },
        "type": "split_by_contact_field"
      },
      "540b0a25-c9a4-4521-8863-69d243f0a0d6": {
        "config": {
          "cases": {},
          "operand": {
            "id": "age_group_for_tips",
            "name": "age group for tips",
            "type": "field"
          }
        },
        "position": {
          "left": 1160,
          "top": 1120
        },
        "type": "split_by_contact_field"
      },
      "3cdc6dbc-126b-4282-8ecf-aa9777477944": {
        "config": {},
        "position": {
          "left": 320,
          "top": 1160
        },
        "type": "split_by_subflow"
      },
      "e951b66f-9011-4a3c-a47a-5ef96f247135": {
        "config": {},
        "position": {
          "left": 40,
          "top": 1240
        },
        "type": "split_by_subflow"
      },
      "f4ac1885-7de2-4197-af4b-5eb0995e7046": {
        "config": {},
        "position": {
          "left": 920,
          "top": 1240
        },
        "type": "split_by_subflow"
      },
      "c1620dc8-2b6d-479e-bf9f-e5ed1e0529b3": {
        "type": "split_by_subflow",
        "position": {
          "left": 1180,
          "top": 1240
        },
        "config": {}
      },
      "b8a1f401-2d77-4689-ab65-98c058ac3a35": {
        "config": {},
        "position": {
          "left": 760,
          "top": 1400
        },
        "type": "split_by_subflow"
      },
      "271c1218-7fc4-4991-bd06-2fb5d15219a8": {
        "config": {},
        "position": {
          "left": 1000,
          "top": 1400
        },
        "type": "split_by_subflow"
      },
      "35f05fba-0069-4755-be09-7a274ffe06c6": {
        "config": {},
        "position": {
          "left": 1240,
          "top": 1400
        },
        "type": "split_by_subflow"
      },
      "b050ae77-dd48-4ce6-8fcc-8e187aae0b45": {
        "config": {
          "cases": {},
          "operand": {
            "id": "age_group_for_tips",
            "name": "age group for tips",
            "type": "field"
          }
        },
        "position": {
          "left": 80,
          "top": 1580
        },
        "type": "split_by_contact_field"
      },
      "af9859b1-7e91-47bc-b460-14b7197c39f4": {
        "position": {
          "left": 940,
          "top": 1600
        },
        "type": "execute_actions"
      },
      "4207d3fc-d207-4f85-99a9-95e457604489": {
        "type": "split_by_contact_field",
        "position": {
          "left": 500,
          "top": 1640
        },
        "config": {
          "operand": {
            "id": "next_tip_main",
            "type": "field",
            "name": "next tip main"
          },
          "cases": {}
        }
      },
      "7a2088b1-74dd-4431-ace7-5a7f1ed67b05": {
        "config": {},
        "position": {
          "left": 60,
          "top": 1700
        },
        "type": "split_by_subflow"
      },
      "d0a71643-2a3e-4d77-b021-d2f60f408837": {
        "config": {
          "cases": {},
          "operand": {
            "id": "age_group_for_tips",
            "name": "age group for tips",
            "type": "field"
          }
        },
        "position": {
          "left": 560,
          "top": 1780
        },
        "type": "split_by_contact_field"
      },
      "37d06de9-9716-423f-a511-c70418af2f21": {
        "config": {},
        "position": {
          "left": 80,
          "top": 1860
        },
        "type": "split_by_subflow"
      },
      "db7afc44-fa0f-4369-95a9-236a228f7923": {
        "config": {},
        "position": {
          "left": 800,
          "top": 1860
        },
        "type": "split_by_subflow"
      },
      "3042bac4-f5d3-4508-8c7f-9ab47af7c99a": {
        "config": {},
        "position": {
          "left": 500,
          "top": 1900
        },
        "type": "split_by_subflow"
      },
      "70805de3-56fb-42a9-a115-6b6f074176a6": {
        "config": {},
        "position": {
          "left": 1080,
          "top": 1900
        },
        "type": "split_by_subflow"
      },
      "93b8d31b-5309-4470-83d4-167209e64ca8": {
        "type": "split_by_subflow",
        "position": {
          "left": 240,
          "top": 2060
        },
        "config": {}
      },
      "98a20f9c-0c09-4afc-8f8a-2bee3c264e6f": {
        "config": {},
        "position": {
          "left": 800,
          "top": 2160
        },
        "type": "split_by_subflow"
      }
    },
    "stickies": {}
  },
  "expire_after_minutes": 60,
  "ignore_triggers": true,
  "language": "eng",
  "localization": {},
  "metadata": {
    "revision": 53
  },
  "name": "PLH - Handler - Content - Main - Positive",
  "nodes": [
    {
      "actions": [],
      "exits": [
        {
          "destination_uuid": "41e98aa6-a4bb-4cf1-b21c-c7ddb582e228",
          "uuid": "7b168e19-fcee-4d9f-9cde-5268792d254d"
        },
        {
          "destination_uuid": "2edc04f6-03f7-46ff-a68c-36d22a40a9c4",
          "uuid": "a6e37a8c-7858-4851-ab4b-c418b066d844"
        },
        {
          "destination_uuid": "480a1258-2f9d-4401-acf2-e1085ba45c21",
          "uuid": "4f0541f9-7063-4d8c-a513-ad9778e7b91a"
        },
        {
          "destination_uuid": "96a9ecfc-2b1c-48ce-b441-8df70165d5a6",
          "uuid": "abd87166-f11d-49ec-882e-9e21f8606cb4"
        },
        {
          "destination_uuid": "236c22cb-179c-4775-8547-53a5788d4c3d",
          "uuid": "155f5cdf-b685-448b-b682-84f67af7d3d8"
        },
        {
          "destination_uuid": "286d0c22-5644-4d98-9654-8a4eee868644",
          "uuid": "56b01050-4e17-4e4e-acb6-601092b5ff2d"
        },
        {
          "destination_uuid": "dd83c325-2c09-4e6c-9934-3f2a999a6c08",
          "uuid": "0686767d-b2bf-4a6f-9dba-63c1f3c20a7b"
        }
      ],
      "router": {
        "cases": [
          {
            "arguments": [
              "4"
            ],
            "category_uuid": "84f81fd2-38ef-4f02-9866-eecfe232666e",
            "type": "has_number_eq",
            "uuid": "dc49f8f5-5d32-424e-9e48-04ed9760f334"
          },
          {
            "arguments": [
              "5"
            ],
            "category_uuid": "3f6b0593-157d-459f-aa27-785acf450df2",
            "type": "has_number_eq",
            "uuid": "9f958ab6-2fb7-45cb-bc13-163b182cb305"
          },
          {
            "arguments": [
              "6"
            ],
            "category_uuid": "6926fc2a-b819-4ac6-a530-75ca0b52c516",
            "type": "has_any_word",
            "uuid": "03de9d92-cfcd-4ce4-b725-602453086632"
          },
          {
            "arguments": [
              "7"
            ],
            "category_uuid": "6df0bcf5-e093-45a5-8dd0-ead9d6cb4467",
            "type": "has_any_word",
            "uuid": "d720506b-e4bf-4ed1-b04c-65345ff85815"
          },
          {
            "arguments": [
              "8"
            ],
            "category_uuid": "246d4b57-6f3e-4863-a9ea-4d64dd87695a",
            "type": "has_any_word",
            "uuid": "6b6a8bcc-19df-4221-af3d-a885534bb7a2"
          },
          {
            "arguments": [
              "9"
            ],
            "category_uuid": "d9ddfbfb-3ce1-4cef-9eeb-712d5868e975",
            "type": "has_any_word",
            "uuid": "caaa8df0-ab0a-4fc6-8f3a-d93b3233b962"
          }
        ],
        "categories": [
          {
            "exit_uuid": "7b168e19-fcee-4d9f-9cde-5268792d254d",
            "name": "4",
            "uuid": "84f81fd2-38ef-4f02-9866-eecfe232666e"
          },
          {
            "exit_uuid": "a6e37a8c-7858-4851-ab4b-c418b066d844",
            "name": "5",
            "uuid": "3f6b0593-157d-459f-aa27-785acf450df2"
          },
          {
            "exit_uuid": "4f0541f9-7063-4d8c-a513-ad9778e7b91a",
            "name": "6",
            "uuid": "6926fc2a-b819-4ac6-a530-75ca0b52c516"
          },
          {
            "exit_uuid": "abd87166-f11d-49ec-882e-9e21f8606cb4",
            "name": "7",
            "uuid": "6df0bcf5-e093-45a5-8dd0-ead9d6cb4467"
          },
          {
            "exit_uuid": "155f5cdf-b685-448b-b682-84f67af7d3d8",
            "name": "8",
            "uuid": "246d4b57-6f3e-4863-a9ea-4d64dd87695a"
          },
          {
            "exit_uuid": "56b01050-4e17-4e4e-acb6-601092b5ff2d",
            "name": "9",
            "uuid": "d9ddfbfb-3ce1-4cef-9eeb-712d5868e975"
          },
          {
            "exit_uuid": "0686767d-b2bf-4a6f-9dba-63c1f3c20a7b",
            "name": "Other",
            "uuid": "e20c66eb-fd62-481b-9ce8-846d594cd3fc"
          }
        ],
        "default_category_uuid": "e20c66eb-fd62-481b-9ce8-846d594cd3fc",
        "operand": "@fields.next_tip_main",
        "type": "switch"
      },
      "uuid": "ebb0892f-b657-4094-a934-f29d006f11c7"
    },
    {
      "uuid": "236c22cb-179c-4775-8547-53a5788d4c3d",
      "actions": [],
      "router": {
        "type": "switch",
        "default_category_uuid": "072150a0-c1b9-482b-8bd3-6818a20684e9",
        "cases": [
          {
            "arguments": [
              "yes"
            ],
            "type": "has_any_word",
            "uuid": "86362fc3-3e67-45e5-a9dd-6771aa9ff06e",
            "category_uuid": "4032976f-f2f4-4164-a0fc-27c45995c027"
          }
        ],
        "categories": [
          {
            "uuid": "4032976f-f2f4-4164-a0fc-27c45995c027",
            "name": "Yes",
            "exit_uuid": "c1e5270d-0cec-474b-a059-78da7d955790"
          },
          {
            "uuid": "072150a0-c1b9-482b-8bd3-6818a20684e9",
            "name": "Other",
            "exit_uuid": "eb1c63d4-5478-4fee-b24c-4f2a1ddcae15"
          }
        ],
        "operand": "@fields.get_ipv_content"
      },
      "exits": [
        {
          "uuid": "c1e5270d-0cec-474b-a059-78da7d955790",
          "destination_uuid": "61ffef4e-1fba-4c6a-b24b-9db7ddd5ddd6"
        },
        {
          "uuid": "eb1c63d4-5478-4fee-b24c-4f2a1ddcae15",
          "destination_uuid": "8fdd3f12-cb40-442e-b0b7-41bd7ca6e53c"
        }
      ]
    },
    {
      "actions": [
        {
          "flow": {
            "name": "PLH - Content - Positive - Education - Timed intro",
            "uuid": "77fc6ec8-4697-4616-88e4-60149dee837f"
          },
          "type": "enter_flow",
          "uuid": "39647552-7aa6-45ae-ad5b-4528843082b8"
        }
      ],
      "exits": [
        {
          "destination_uuid": null,
          "uuid": "9da13684-01c2-428f-9e50-f7d07204ff22"
        },
        {
          "destination_uuid": "d0bc8187-3a70-409b-b12b-a1abe9ac76af",
          "uuid": "4bee002d-70e2-4d4c-afad-59c75a9d47b6"
        }
      ],
      "router": {
        "cases": [
          {
            "arguments": [
              "completed"
            ],
            "category_uuid": "923fcc7e-51dc-4d28-a9f3-507d1d1bfbaa",
            "type": "has_only_text",
            "uuid": "23e8f778-6ca6-48b9-bed8-a287b91503b6"
          },
          {
            "arguments": [
              "expired"
            ],
            "category_uuid": "d88f2842-2422-4370-aef6-9ab240dd3033",
            "type": "has_only_text",
            "uuid": "bce1aa05-58e1-4820-9940-d547f7f88bcf"
          }
        ],
        "categories": [
          {
            "exit_uuid": "9da13684-01c2-428f-9e50-f7d07204ff22",
            "name": "Complete",
            "uuid": "923fcc7e-51dc-4d28-a9f3-507d1d1bfbaa"
          },
          {
            "exit_uuid": "4bee002d-70e2-4d4c-afad-59c75a9d47b6",
            "name": "Expired",
            "uuid": "d88f2842-2422-4370-aef6-9ab240dd3033"
          }
        ],
        "default_category_uuid": "d88f2842-2422-4370-aef6-9ab240dd3033",
        "operand": "@child.run.status",
        "type": "switch"
      },
      "uuid": "286d0c22-5644-4d98-9654-8a4eee868644"
    },
    {
      "actions": [
        {
          "flow": {
            "name": "PLH - Content - Positive - Introduction",
            "uuid": "afaf6a89-ab4b-410e-935b-0c0138957a52"
          },
          "type": "enter_flow",
          "uuid": "fd558ab4-27f5-4908-8b2a-dc6b8a456f19"
        }
      ],
      "exits": [
        {
          "destination_uuid": null,
          "uuid": "e7c6b0e0-59da-4970-9d03-690d6f1e8522"
        },
        {
          "destination_uuid": "d0bc8187-3a70-409b-b12b-a1abe9ac76af",
          "uuid": "57242f89-6bcc-4aae-acd0-a5706ba031c9"
        }
      ],
      "router": {
        "cases": [
          {
            "arguments": [
              "completed"
            ],
            "category_uuid": "3b3a01e1-099c-4f0d-9ce3-79027b4dc086",
            "type": "has_only_text",
            "uuid": "e221a9a2-ef65-461d-ba0c-841fae971e78"
          },
          {
            "arguments": [
              "expired"
            ],
            "category_uuid": "f784cbef-e208-46cf-8018-c693fe8108f0",
            "type": "has_only_text",
            "uuid": "d5889c70-3591-4b18-8e08-0f132a689912"
          }
        ],
        "categories": [
          {
            "exit_uuid": "e7c6b0e0-59da-4970-9d03-690d6f1e8522",
            "name": "Complete",
            "uuid": "3b3a01e1-099c-4f0d-9ce3-79027b4dc086"
          },
          {
            "exit_uuid": "57242f89-6bcc-4aae-acd0-a5706ba031c9",
            "name": "Expired",
            "uuid": "f784cbef-e208-46cf-8018-c693fe8108f0"
          }
        ],
        "default_category_uuid": "f784cbef-e208-46cf-8018-c693fe8108f0",
        "operand": "@child.run.status",
        "type": "switch"
      },
      "uuid": "41e98aa6-a4bb-4cf1-b21c-c7ddb582e228"
    },
    {
      "actions": [],
      "exits": [
        {
          "destination_uuid": "4c10cd29-35de-4e82-bfd8-7af1f44c5257",
          "uuid": "e6e622c2-ea59-46cd-be10-97d6c5011080"
        },
        {
          "destination_uuid": "8329a0e5-97a6-4e9a-ad7e-fa173cc0d9a2",
          "uuid": "681e9854-ca1b-4cec-95d1-a8a36e0cd900"
        }
      ],
      "router": {
        "cases": [
          {
            "arguments": [
              "baby"
            ],
            "category_uuid": "4343f142-a289-4f4f-9b73-6347fa198e95",
            "type": "has_any_word",
            "uuid": "faf7940e-26c6-4349-b5c5-64bcf74b1c38"
          }
        ],
        "categories": [
          {
            "exit_uuid": "e6e622c2-ea59-46cd-be10-97d6c5011080",
            "name": "Baby",
            "uuid": "4343f142-a289-4f4f-9b73-6347fa198e95"
          },
          {
            "exit_uuid": "681e9854-ca1b-4cec-95d1-a8a36e0cd900",
            "name": "Other",
            "uuid": "b01df244-bcd5-4694-b844-678fee1ace8a"
          }
        ],
        "default_category_uuid": "b01df244-bcd5-4694-b844-678fee1ace8a",
        "operand": "@fields.age_group_for_tips",
        "type": "switch"
      },
      "uuid": "2edc04f6-03f7-46ff-a68c-36d22a40a9c4"
    },
    {
      "actions": [
        {
          "flow": {
            "name": "PLH - Content - Positive - Behave - Routines - Timed intro",
            "uuid": "04d446a8-a4f3-45dc-b1d7-d9749682f6f0"
          },
          "type": "enter_flow",
          "uuid": "10a9752f-a6cc-4ae6-a5a5-c521a0360571"
        }
      ],
      "exits": [
        {
          "destination_uuid": null,
          "uuid": "0216b3d7-974a-4cc2-a11a-edfe5cc8919c"
        },
        {
          "destination_uuid": "d0bc8187-3a70-409b-b12b-a1abe9ac76af",
          "uuid": "ef4078a7-99c7-414b-834b-6cc5a5fbdbd6"
        }
      ],
      "router": {
        "cases": [
          {
            "arguments": [
              "completed"
            ],
            "category_uuid": "8c0ad8d6-c194-444a-93f1-29fa943a865c",
            "type": "has_only_text",
            "uuid": "db2df2a4-d287-4038-93d0-733327b7c103"
          },
          {
            "arguments": [
              "expired"
            ],
            "category_uuid": "1f21d37c-16d9-44c2-9e2f-b25095ab25fb",
            "type": "has_only_text",
            "uuid": "cf6c98cb-9f44-414d-878f-43079cad0007"
          }
        ],
        "categories": [
          {
            "exit_uuid": "0216b3d7-974a-4cc2-a11a-edfe5cc8919c",
            "name": "Complete",
            "uuid": "8c0ad8d6-c194-444a-93f1-29fa943a865c"
          },
          {
            "exit_uuid": "ef4078a7-99c7-414b-834b-6cc5a5fbdbd6",
            "name": "Expired",
            "uuid": "1f21d37c-16d9-44c2-9e2f-b25095ab25fb"
          }
        ],
        "default_category_uuid": "1f21d37c-16d9-44c2-9e2f-b25095ab25fb",
        "operand": "@child.run.status",
        "type": "switch"
      },
      "uuid": "96a9ecfc-2b1c-48ce-b441-8df70165d5a6"
    },
    {
      "actions": [
        {
          "flow": {
            "name": "PLH - Content - Positive - Family - Timed intro",
            "uuid": "ea204181-4853-488e-bba1-f7690fd04c66"
          },
          "type": "enter_flow",
          "uuid": "a1bc2dc4-6c76-4960-a11f-b33f98e971c8"
        }
      ],
      "exits": [
        {
          "destination_uuid": null,
          "uuid": "d1f087da-0e6d-46a4-8e69-74b1a5278f31"
        },
        {
          "destination_uuid": "d0bc8187-3a70-409b-b12b-a1abe9ac76af",
          "uuid": "33abc777-b680-4a9c-ad95-4cbd4bf6f7ea"
        }
      ],
      "router": {
        "cases": [
          {
            "arguments": [
              "completed"
            ],
            "category_uuid": "2a694b8d-33c9-4c2c-9350-933f805dbbd4",
            "type": "has_only_text",
            "uuid": "fb8f1bde-2977-4ce8-93b3-49ca5ba04502"
          },
          {
            "arguments": [
              "expired"
            ],
            "category_uuid": "32255b88-3a37-4d4e-81ee-e250c85b8aef",
            "type": "has_only_text",
            "uuid": "8f3dc736-18f0-4610-9b5f-ed468e4e1f97"
          }
        ],
        "categories": [
          {
            "exit_uuid": "d1f087da-0e6d-46a4-8e69-74b1a5278f31",
            "name": "Complete",
            "uuid": "2a694b8d-33c9-4c2c-9350-933f805dbbd4"
          },
          {
            "exit_uuid": "33abc777-b680-4a9c-ad95-4cbd4bf6f7ea",
            "name": "Expired",
            "uuid": "32255b88-3a37-4d4e-81ee-e250c85b8aef"
          }
        ],
        "default_category_uuid": "32255b88-3a37-4d4e-81ee-e250c85b8aef",
        "operand": "@child.run.status",
        "type": "switch"
      },
      "uuid": "8fdd3f12-cb40-442e-b0b7-41bd7ca6e53c"
    },
    {
      "uuid": "61ffef4e-1fba-4c6a-b24b-9db7ddd5ddd6",
      "actions": [
        {
          "uuid": "0ebed0f5-d028-4785-8514-465ee0e2a2a2",
          "type": "enter_flow",
          "flow": {
            "uuid": "902cc573-5ec6-43f3-8ebd-57a042bf1cf2",
            "name": "PLH - Content - Positive - IPV"
          }
        }
      ],
      "router": {
        "type": "switch",
        "operand": "@child.run.status",
        "cases": [
          {
            "uuid": "91dccd7c-a0a6-41d3-8007-b334893ae91c",
            "type": "has_only_text",
            "arguments": [
              "completed"
            ],
            "category_uuid": "5736cfdf-7464-4990-a28a-f02d9f91de64"
          },
          {
            "uuid": "4c5a2125-493a-40c8-bfa4-25f75657a3d8",
            "arguments": [
              "expired"
            ],
            "type": "has_only_text",
            "category_uuid": "d342e7a7-6722-4e88-a6fe-911c9a2dc85e"
          }
        ],
        "categories": [
          {
            "uuid": "5736cfdf-7464-4990-a28a-f02d9f91de64",
            "name": "Complete",
            "exit_uuid": "06976e8a-dc64-41bb-b186-87001ee854d5"
          },
          {
            "uuid": "d342e7a7-6722-4e88-a6fe-911c9a2dc85e",
            "name": "Expired",
            "exit_uuid": "50dbcd25-6b7e-4cc9-9bef-169f6195706d"
          }
        ],
        "default_category_uuid": "d342e7a7-6722-4e88-a6fe-911c9a2dc85e"
      },
      "exits": [
        {
          "uuid": "06976e8a-dc64-41bb-b186-87001ee854d5",
          "destination_uuid": null
        },
        {
          "uuid": "50dbcd25-6b7e-4cc9-9bef-169f6195706d",
          "destination_uuid": "d0bc8187-3a70-409b-b12b-a1abe9ac76af"
        }
      ]
    },
    {
      "actions": [
        {
          "flow": {
            "name": "PLH - Supportive - Activities for babies",
            "uuid": "f11b99bb-15a8-4120-b767-df879ba708d7"
          },
          "type": "enter_flow",
          "uuid": "b413f8f0-652f-4e5d-8fd5-c940885ce21d"
        }
      ],
      "exits": [
        {
          "destination_uuid": null,
          "uuid": "4b870e6f-0400-4065-8853-5d63309c0cf4"
        },
        {
          "destination_uuid": null,
          "uuid": "a42e7d9f-56a3-4957-9a0f-e1113eeafaa3"
        }
      ],
      "router": {
        "cases": [
          {
            "arguments": [
              "completed"
            ],
            "category_uuid": "110a983f-f1ce-4ff5-a4cb-0e5b81087060",
            "type": "has_only_text",
            "uuid": "a5074af3-452d-466a-ac19-6e845976a1a5"
          },
          {
            "arguments": [
              "expired"
            ],
            "category_uuid": "61c85874-f295-4cee-b9d3-7361f524de6c",
            "type": "has_only_text",
            "uuid": "d6b126d6-b5ff-4f02-a7c5-b689917e8052"
          }
        ],
        "categories": [
          {
            "exit_uuid": "4b870e6f-0400-4065-8853-5d63309c0cf4",
            "name": "Complete",
            "uuid": "110a983f-f1ce-4ff5-a4cb-0e5b81087060"
          },
          {
            "exit_uuid": "a42e7d9f-56a3-4957-9a0f-e1113eeafaa3",
            "name": "Expired",
            "uuid": "61c85874-f295-4cee-b9d3-7361f524de6c"
          }
        ],
        "default_category_uuid": "61c85874-f295-4cee-b9d3-7361f524de6c",
        "operand": "@child.run.status",
        "type": "switch"
      },
      "uuid": "4c10cd29-35de-4e82-bfd8-7af1f44c5257"
    },
    {
      "actions": [
        {
          "field": {
            "key": "has_expired",
            "name": "has expired"
          },
          "type": "set_contact_field",
          "uuid": "ff7cdb46-51d1-4ee1-92ad-e2a5da805ad3",
          "value": "tip"
        }
      ],
      "exits": [
        {
          "destination_uuid": "846d24dd-f48f-417b-800c-8a35c4b149ef",
          "uuid": "9e078a33-b048-4f70-a610-ca8652834e70"
        }
      ],
      "uuid": "d0bc8187-3a70-409b-b12b-a1abe9ac76af"
    },
    {
      "actions": [],
      "exits": [
        {
          "destination_uuid": "fdfa88f1-b1f8-4cb3-9733-3fea1fa83e8e",
          "uuid": "d770149c-1c13-4419-a5b0-6b2203ad33a2"
        },
        {
          "destination_uuid": "49ffd29f-3b40-44e7-a94f-24414ad40856",
          "uuid": "28f969dc-1afb-4be0-80ab-54d202bc72bd"
        }
      ],
      "router": {
        "cases": [
          {
            "arguments": [
              "baby"
            ],
            "category_uuid": "db4600c3-b04b-46c7-ab77-8ebe11d3447e",
            "type": "has_any_word",
            "uuid": "44641db9-6ad5-465e-8cef-e5623a2e7334"
          }
        ],
        "categories": [
          {
            "exit_uuid": "d770149c-1c13-4419-a5b0-6b2203ad33a2",
            "name": "Baby",
            "uuid": "db4600c3-b04b-46c7-ab77-8ebe11d3447e"
          },
          {
            "exit_uuid": "28f969dc-1afb-4be0-80ab-54d202bc72bd",
            "name": "Other",
            "uuid": "73e5c928-8d8d-47e1-81a3-d093e2d01ba0"
          }
        ],
        "default_category_uuid": "73e5c928-8d8d-47e1-81a3-d093e2d01ba0",
        "operand": "@fields.age_group_for_tips",
        "type": "switch"
      },
      "uuid": "480a1258-2f9d-4401-acf2-e1085ba45c21"
    },
    {
      "actions": [
        {
          "flow": {
            "name": "PLH - Content - Positive - Positive instructions",
            "uuid": "b1e03180-c408-4311-8ebe-fbbaf623d635"
          },
          "type": "enter_flow",
          "uuid": "cab6a876-60e0-4e48-b429-ed718b102cdf"
        }
      ],
      "exits": [
        {
          "destination_uuid": null,
          "uuid": "5f514f64-9400-4d1e-9475-45a37967c405"
        },
        {
          "destination_uuid": "d0bc8187-3a70-409b-b12b-a1abe9ac76af",
          "uuid": "3b970428-68b3-4a90-a50b-c2517b1b8c08"
        }
      ],
      "router": {
        "cases": [
          {
            "arguments": [
              "completed"
            ],
            "category_uuid": "5e791a34-d6cc-44a1-91ba-95101584d1a0",
            "type": "has_only_text",
            "uuid": "ee764a59-d19a-4c7f-a67d-13d44a31be59"
          },
          {
            "arguments": [
              "expired"
            ],
            "category_uuid": "3a07e0df-94d7-4acb-9446-2dd95ce6ca7b",
            "type": "has_only_text",
            "uuid": "ea4cdcb8-3ae4-4adc-809c-d52af861eee6"
          }
        ],
        "categories": [
          {
            "exit_uuid": "5f514f64-9400-4d1e-9475-45a37967c405",
            "name": "Complete",
            "uuid": "5e791a34-d6cc-44a1-91ba-95101584d1a0"
          },
          {
            "exit_uuid": "3b970428-68b3-4a90-a50b-c2517b1b8c08",
            "name": "Expired",
            "uuid": "3a07e0df-94d7-4acb-9446-2dd95ce6ca7b"
          }
        ],
        "default_category_uuid": "3a07e0df-94d7-4acb-9446-2dd95ce6ca7b",
        "operand": "@child.run.status",
        "type": "switch"
      },
      "uuid": "8329a0e5-97a6-4e9a-ad7e-fa173cc0d9a2"
    },
    {
      "actions": [
        {
          "all_urns": false,
          "attachments": [],
          "quick_replies": [],
          "text": "It looks like you are busy right now. You can always type \"GoBack\" to restart this parenting tip or \"Help\" for other support.",
          "type": "send_msg",
          "uuid": "6936661f-8f5b-4e69-8408-b4377591b44b"
        }
      ],
      "exits": [
        {
          "destination_uuid": null,
          "uuid": "277ccc0b-7a23-43c4-871e-6860ff55ef7a"
        }
      ],
      "uuid": "846d24dd-f48f-417b-800c-8a35c4b149ef"
    },
    {
      "actions": [
        {
          "flow": {
            "name": "PLH - Content - Positive - Book sharing - Timed intro",
            "uuid": "c8fe4261-f046-499a-87b8-02b0d6f832c4"
          },
          "type": "enter_flow",
          "uuid": "e05062b7-ea06-4825-8c24-30648ce7291f"
        }
      ],
      "exits": [
        {
          "destination_uuid": null,
          "uuid": "42ff4862-7856-46c5-9c00-a342bcf15226"
        },
        {
          "destination_uuid": "d0bc8187-3a70-409b-b12b-a1abe9ac76af",
          "uuid": "da8dc77a-e3e6-4194-9560-cc63b7f3e846"
        }
      ],
      "router": {
        "cases": [
          {
            "arguments": [
              "completed"
            ],
            "category_uuid": "6dedc343-6b27-4423-8d23-075145b9a520",
            "type": "has_only_text",
            "uuid": "10232123-93df-4052-8394-9f67a0e7d5c8"
          },
          {
            "arguments": [
              "expired"
            ],
            "category_uuid": "ffe2ead9-bf46-40e8-95db-747a0f7d4d1f",
            "type": "has_only_text",
            "uuid": "8c950d41-c691-4c2a-9ddd-9372dfbad48e"
          }
        ],
        "categories": [
          {
            "exit_uuid": "42ff4862-7856-46c5-9c00-a342bcf15226",
            "name": "Complete",
            "uuid": "6dedc343-6b27-4423-8d23-075145b9a520"
          },
          {
            "exit_uuid": "da8dc77a-e3e6-4194-9560-cc63b7f3e846",
            "name": "Expired",
            "uuid": "ffe2ead9-bf46-40e8-95db-747a0f7d4d1f"
          }
        ],
        "default_category_uuid": "ffe2ead9-bf46-40e8-95db-747a0f7d4d1f",
        "operand": "@child.run.status",
        "type": "switch"
      },
      "uuid": "fdfa88f1-b1f8-4cb3-9733-3fea1fa83e8e"
    },
    {
      "actions": [
        {
          "flow": {
            "name": "PLH - Content - Positive - Behave - Praise - Timed intro",
            "uuid": "99fa3778-38a3-4135-8e06-0766f70e5b32"
          },
          "type": "enter_flow",
          "uuid": "5344b6c7-3d1b-403d-ab79-f4e6bc32d69d"
        }
      ],
      "exits": [
        {
          "destination_uuid": null,
          "uuid": "feede6e0-6a95-4acb-8c3e-c459d9e5b036"
        },
        {
          "destination_uuid": "d0bc8187-3a70-409b-b12b-a1abe9ac76af",
          "uuid": "4cc664ef-f18d-48f1-a2b7-8b9bef0db5d0"
        }
      ],
      "router": {
        "cases": [
          {
            "arguments": [
              "completed"
            ],
            "category_uuid": "df47e309-04a8-42bf-a278-d38b6f9fab76",
            "type": "has_only_text",
            "uuid": "170caa0d-8d95-429a-857a-8debfda88123"
          },
          {
            "arguments": [
              "expired"
            ],
            "category_uuid": "65d0ec56-484e-4ad9-9f15-79fff5ad35af",
            "type": "has_only_text",
            "uuid": "1ad9a4d8-db8a-483d-89f4-ca4e1a1a8bec"
          }
        ],
        "categories": [
          {
            "exit_uuid": "feede6e0-6a95-4acb-8c3e-c459d9e5b036",
            "name": "Complete",
            "uuid": "df47e309-04a8-42bf-a278-d38b6f9fab76"
          },
          {
            "exit_uuid": "4cc664ef-f18d-48f1-a2b7-8b9bef0db5d0",
            "name": "Expired",
            "uuid": "65d0ec56-484e-4ad9-9f15-79fff5ad35af"
          }
        ],
        "default_category_uuid": "65d0ec56-484e-4ad9-9f15-79fff5ad35af",
        "operand": "@child.run.status",
        "type": "switch"
      },
      "uuid": "49ffd29f-3b40-44e7-a94f-24414ad40856"
    },
    {
      "actions": [],
      "exits": [
        {
          "destination_uuid": "9eeea984-02e4-4d02-9ec9-80e25e5d4f7c",
          "uuid": "38ba1836-6eaf-4e9a-a845-19570361178f"
        },
        {
          "destination_uuid": "7b720b86-12ef-4692-95f0-025a9ba60996",
          "uuid": "ff917661-8d4c-4444-b379-6dc990d1afe5"
        }
      ],
      "router": {
        "cases": [
          {
            "arguments": [
              "baby"
            ],
            "category_uuid": "45a36b3a-e8e6-4883-8fe0-b490b781140a",
            "type": "has_any_word",
            "uuid": "68d6b5ef-e978-483e-afd5-29a5bca8e757"
          }
        ],
        "categories": [
          {
            "exit_uuid": "38ba1836-6eaf-4e9a-a845-19570361178f",
            "name": "Baby",
            "uuid": "45a36b3a-e8e6-4883-8fe0-b490b781140a"
          },
          {
            "exit_uuid": "ff917661-8d4c-4444-b379-6dc990d1afe5",
            "name": "Other",
            "uuid": "487280f0-15bd-430b-ad2e-8ba86464a437"
          }
        ],
        "default_category_uuid": "487280f0-15bd-430b-ad2e-8ba86464a437",
        "operand": "@fields.age_group_for_tips",
        "type": "switch"
      },
      "uuid": "18520cad-e755-46da-b872-f412e1528904"
    },
    {
      "uuid": "dd83c325-2c09-4e6c-9934-3f2a999a6c08",
      "actions": [],
      "router": {
        "type": "switch",
        "default_category_uuid": "00a73c9e-fd69-4683-8ae8-2431c28f38dc",
        "cases": [
          {
            "arguments": [
              "10"
            ],
            "type": "has_any_word",
            "uuid": "ce5463af-5fe7-4357-811a-d277e7677f7d",
            "category_uuid": "c8abeec1-e5a8-49a0-a0b0-b6d527973449"
          },
          {
            "arguments": [
              "11"
            ],
            "type": "has_any_word",
            "uuid": "0b2cdee1-c7a5-4d9e-97ff-fb3020b25aa1",
            "category_uuid": "9ee4f042-0fa9-4ec0-abf8-6cad9597fa2a"
          },
          {
            "arguments": [
              "12"
            ],
            "type": "has_any_word",
            "uuid": "a8f4103e-50f1-424d-9167-36e51f935abb",
            "category_uuid": "9b0c8457-98f9-4919-9cfc-d53b75b90d82"
          },
          {
            "arguments": [
              "13"
            ],
            "type": "has_any_word",
            "uuid": "78d64db2-c4e1-43f8-9a49-bcb29fbec7ac",
            "category_uuid": "342ce26b-f3c4-4add-af19-8b07a992d82c"
          },
          {
            "arguments": [
              "14"
            ],
            "type": "has_any_word",
            "uuid": "060caf1e-5a90-496f-ad96-6731832cc42a",
            "category_uuid": "fa4846c1-bf31-4d65-8b3c-9f125c726e3d"
          },
          {
            "arguments": [
              "15"
            ],
            "type": "has_any_word",
            "uuid": "1dd15427-e01e-40a1-9ec2-23f1c385bcbc",
            "category_uuid": "1df131c0-2b32-4304-9b19-4c96bff85115"
          }
        ],
        "categories": [
          {
            "exit_uuid": "48652aab-bfd4-4d2f-84b3-4ec2e7cae0c8",
            "name": "10",
            "uuid": "c8abeec1-e5a8-49a0-a0b0-b6d527973449"
          },
          {
            "exit_uuid": "be897748-becf-4737-9511-3180e3f26aef",
            "name": "11",
            "uuid": "9ee4f042-0fa9-4ec0-abf8-6cad9597fa2a"
          },
          {
            "exit_uuid": "11503484-675e-431b-aea6-d55c6abb4f0d",
            "name": "12",
            "uuid": "9b0c8457-98f9-4919-9cfc-d53b75b90d82"
          },
          {
            "exit_uuid": "f0be0bdd-37ef-43c2-b325-09601023c994",
            "name": "13",
            "uuid": "342ce26b-f3c4-4add-af19-8b07a992d82c"
          },
          {
            "exit_uuid": "2c216e75-ddbf-4f4a-9c2d-97a66048cfae",
            "name": "14",
            "uuid": "fa4846c1-bf31-4d65-8b3c-9f125c726e3d"
          },
          {
            "uuid": "1df131c0-2b32-4304-9b19-4c96bff85115",
            "name": "15",
            "exit_uuid": "c832aaf3-c80f-44af-a2b5-c7c8038c921c"
          },
          {
            "exit_uuid": "2cf53bf7-089a-4293-a9c5-78cb967bca75",
            "name": "Other",
            "uuid": "00a73c9e-fd69-4683-8ae8-2431c28f38dc"
          }
        ],
        "operand": "@fields.next_tip_main"
      },
      "exits": [
        {
          "destination_uuid": "18520cad-e755-46da-b872-f412e1528904",
          "uuid": "48652aab-bfd4-4d2f-84b3-4ec2e7cae0c8"
        },
        {
          "destination_uuid": "c89ae386-5859-41d1-973d-81885d983b1a",
          "uuid": "be897748-becf-4737-9511-3180e3f26aef"
        },
        {
          "destination_uuid": "3ec246fe-7040-4f45-b292-3113a64de0bc",
          "uuid": "11503484-675e-431b-aea6-d55c6abb4f0d"
        },
        {
          "destination_uuid": "ff94d097-0df5-426f-982f-0d6d812d8937",
          "uuid": "f0be0bdd-37ef-43c2-b325-09601023c994"
        },
        {
          "destination_uuid": "d22d7db9-9537-4617-9099-4a12eaa62566",
          "uuid": "2c216e75-ddbf-4f4a-9c2d-97a66048cfae"
        },
        {
          "uuid": "c832aaf3-c80f-44af-a2b5-c7c8038c921c",
          "destination_uuid": "540b0a25-c9a4-4521-8863-69d243f0a0d6"
        },
        {
          "destination_uuid": "4207d3fc-d207-4f85-99a9-95e457604489",
          "uuid": "2cf53bf7-089a-4293-a9c5-78cb967bca75"
        }
      ]
    },
    {
      "actions": [
        {
          "flow": {
            "name": "PLH - Supportive - Activities for babies",
            "uuid": "f11b99bb-15a8-4120-b767-df879ba708d7"
          },
          "type": "enter_flow",
          "uuid": "a249b14b-eb14-4c30-9d9f-299a02a39011"
        }
      ],
      "exits": [
        {
          "destination_uuid": null,
          "uuid": "f3294bbc-92b1-46ad-8771-07fcdcead579"
        },
        {
          "destination_uuid": null,
          "uuid": "b3d89a56-7ba6-46c4-9cd4-9ed3cbfcaf51"
        }
      ],
      "router": {
        "cases": [
          {
            "arguments": [
              "completed"
            ],
            "category_uuid": "f88a9d08-82d3-41e9-b619-666851a5dc07",
            "type": "has_only_text",
            "uuid": "e46395b5-2577-4019-b318-323fef2fa507"
          },
          {
            "arguments": [
              "expired"
            ],
            "category_uuid": "f2789b93-cc42-4da3-abdc-81a370106bc8",
            "type": "has_only_text",
            "uuid": "dd9581d3-8efe-414b-9444-d4c74c0890f5"
          }
        ],
        "categories": [
          {
            "exit_uuid": "f3294bbc-92b1-46ad-8771-07fcdcead579",
            "name": "Complete",
            "uuid": "f88a9d08-82d3-41e9-b619-666851a5dc07"
          },
          {
            "exit_uuid": "b3d89a56-7ba6-46c4-9cd4-9ed3cbfcaf51",
            "name": "Expired",
            "uuid": "f2789b93-cc42-4da3-abdc-81a370106bc8"
          }
        ],
        "default_category_uuid": "f2789b93-cc42-4da3-abdc-81a370106bc8",
        "operand": "@child.run.status",
        "type": "switch"
      },
      "uuid": "9eeea984-02e4-4d02-9ec9-80e25e5d4f7c"
    },
    {
      "actions": [
        {
          "flow": {
            "name": "PLH - Content - Positive - Rules",
            "uuid": "60b7961b-13a8-4670-a966-748ec8f06766"
          },
          "type": "enter_flow",
          "uuid": "6e556487-e879-4a76-8c37-08b1da425278"
        }
      ],
      "exits": [
        {
          "destination_uuid": null,
          "uuid": "1cfce426-7e91-4ea9-8f6d-7800b964f0ed"
        },
        {
          "destination_uuid": "d0bc8187-3a70-409b-b12b-a1abe9ac76af",
          "uuid": "32e8f889-2d2c-4ff8-ac92-5ab0c2a9edcf"
        }
      ],
      "router": {
        "cases": [
          {
            "arguments": [
              "completed"
            ],
            "category_uuid": "2d809fa0-caf5-4fed-af0a-48d064a26f66",
            "type": "has_only_text",
            "uuid": "91e2e77b-3df5-4398-b7ef-68487863dc2d"
          },
          {
            "arguments": [
              "expired"
            ],
            "category_uuid": "d3f1e00a-e545-46e0-9f09-101b2e04cad4",
            "type": "has_only_text",
            "uuid": "7d5fbbde-8588-4156-933e-61744e908448"
          }
        ],
        "categories": [
          {
            "exit_uuid": "1cfce426-7e91-4ea9-8f6d-7800b964f0ed",
            "name": "Complete",
            "uuid": "2d809fa0-caf5-4fed-af0a-48d064a26f66"
          },
          {
            "exit_uuid": "32e8f889-2d2c-4ff8-ac92-5ab0c2a9edcf",
            "name": "Expired",
            "uuid": "d3f1e00a-e545-46e0-9f09-101b2e04cad4"
          }
        ],
        "default_category_uuid": "d3f1e00a-e545-46e0-9f09-101b2e04cad4",
        "operand": "@child.run.status",
        "type": "switch"
      },
      "uuid": "7b720b86-12ef-4692-95f0-025a9ba60996"
    },
    {
      "actions": [],
      "exits": [
        {
          "destination_uuid": "a23adf12-69fe-4b9b-838c-a924e1848c49",
          "uuid": "78c4d94b-da6a-464c-97d1-e7b88c713bbd"
        },
        {
          "destination_uuid": "3cdc6dbc-126b-4282-8ecf-aa9777477944",
          "uuid": "72e7def4-c901-4c28-bf6d-6f684698f3a2"
        }
      ],
      "router": {
        "cases": [
          {
            "arguments": [
              "baby"
            ],
            "category_uuid": "59a5c8ef-ab9e-4a21-a8ca-22d600a5f18a",
            "type": "has_any_word",
            "uuid": "558c936f-0c68-4c01-b7aa-f2a116f6c8d9"
          }
        ],
        "categories": [
          {
            "exit_uuid": "78c4d94b-da6a-464c-97d1-e7b88c713bbd",
            "name": "Baby",
            "uuid": "59a5c8ef-ab9e-4a21-a8ca-22d600a5f18a"
          },
          {
            "exit_uuid": "72e7def4-c901-4c28-bf6d-6f684698f3a2",
            "name": "Other",
            "uuid": "cf7023fa-1f54-41c8-8fb9-cf4fb17ad7e4"
          }
        ],
        "default_category_uuid": "cf7023fa-1f54-41c8-8fb9-cf4fb17ad7e4",
        "operand": "@fields.age_group_for_tips",
        "type": "switch"
      },
      "uuid": "3ec246fe-7040-4f45-b292-3113a64de0bc"
    },
    {
      "actions": [],
      "exits": [
        {
          "destination_uuid": "4c10cd29-35de-4e82-bfd8-7af1f44c5257",
          "uuid": "40e5f328-1c48-4e60-9ee3-1c1deabbeab4"
        },
        {
          "destination_uuid": "2ab85e63-4e95-4dd8-bad3-e6aa4c76e81c",
          "uuid": "bcaf02b5-01e3-493b-858b-d94a3968a36a"
        },
        {
          "destination_uuid": "b8a1f401-2d77-4689-ab65-98c058ac3a35",
          "uuid": "2b88f73e-afdf-4385-a14c-4c1f28d136f6"
        }
      ],
      "router": {
        "cases": [
          {
            "arguments": [
              "baby"
            ],
            "category_uuid": "3b8d5661-ec3f-4f17-ab52-2ef1b0a6c538",
            "type": "has_any_word",
            "uuid": "6405c6ec-2daf-444f-a61c-67966514ccdc"
          },
          {
            "arguments": [
              "teen"
            ],
            "category_uuid": "121d71b3-35ab-4f30-befb-9113211f2c63",
            "type": "has_any_word",
            "uuid": "cb235c60-6f64-4d8b-990a-bedd142ce311"
          }
        ],
        "categories": [
          {
            "exit_uuid": "40e5f328-1c48-4e60-9ee3-1c1deabbeab4",
            "name": "Baby",
            "uuid": "3b8d5661-ec3f-4f17-ab52-2ef1b0a6c538"
          },
          {
            "exit_uuid": "bcaf02b5-01e3-493b-858b-d94a3968a36a",
            "name": "Teen",
            "uuid": "121d71b3-35ab-4f30-befb-9113211f2c63"
          },
          {
            "exit_uuid": "2b88f73e-afdf-4385-a14c-4c1f28d136f6",
            "name": "Other",
            "uuid": "1b4c37b5-7209-4dd6-8ded-f3564268348b"
          }
        ],
        "default_category_uuid": "1b4c37b5-7209-4dd6-8ded-f3564268348b",
        "operand": "@fields.age_group_for_tips",
        "type": "switch"
      },
      "uuid": "ff94d097-0df5-426f-982f-0d6d812d8937"
    },
    {
      "actions": [],
      "exits": [
        {
          "destination_uuid": "e951b66f-9011-4a3c-a47a-5ef96f247135",
          "uuid": "80f6f3a2-3a0d-44c6-ab9b-830d522ac49f"
        },
        {
          "destination_uuid": "f6bbe8c7-b30f-4008-a9a7-ebc11c228046",
          "uuid": "bb29972c-8b1a-480b-bdd7-a55b489249ed"
        }
      ],
      "router": {
        "cases": [
          {
            "arguments": [
              "teen"
            ],
            "category_uuid": "3e0aa266-92f8-406f-bb21-481e214fbdb8",
            "type": "has_any_word",
            "uuid": "e23cc5e5-ec73-4869-ac24-3c2ba0413f30"
          }
        ],
        "categories": [
          {
            "exit_uuid": "80f6f3a2-3a0d-44c6-ab9b-830d522ac49f",
            "name": "Teen",
            "uuid": "3e0aa266-92f8-406f-bb21-481e214fbdb8"
          },
          {
            "exit_uuid": "bb29972c-8b1a-480b-bdd7-a55b489249ed",
            "name": "Other",
            "uuid": "fd4bc46a-6c92-480e-8eed-86bb8206055a"
          }
        ],
        "default_category_uuid": "fd4bc46a-6c92-480e-8eed-86bb8206055a",
        "operand": "@fields.age_group_for_tips",
        "type": "switch"
      },
      "uuid": "c89ae386-5859-41d1-973d-81885d983b1a"
    },
    {
      "actions": [
        {
          "flow": {
            "name": "PLH - Supportive - Help reminder",
            "uuid": "8d48227f-e7a0-4aa6-a29e-d9370ca061e0"
          },
          "type": "enter_flow",
          "uuid": "6bd135aa-1ab5-4c42-b689-cb0b8a2c700a"
        }
      ],
      "exits": [
        {
          "destination_uuid": null,
          "uuid": "ff20a12a-1ffe-462f-b4fb-52761164caba"
        },
        {
          "destination_uuid": null,
          "uuid": "b41fdf01-eb81-4525-a113-9ef22e1dfa74"
        }
      ],
      "router": {
        "cases": [
          {
            "arguments": [
              "completed"
            ],
            "category_uuid": "ee36b2fa-0af4-4b31-aeed-56f18b26158b",
            "type": "has_only_text",
            "uuid": "ab96f86e-2e89-428b-9271-0664084e7905"
          },
          {
            "arguments": [
              "expired"
            ],
            "category_uuid": "acb78524-568a-4959-9e56-0452cf33313b",
            "type": "has_only_text",
            "uuid": "92708988-0faa-4fbd-ac73-bf0c21e37652"
          }
        ],
        "categories": [
          {
            "exit_uuid": "ff20a12a-1ffe-462f-b4fb-52761164caba",
            "name": "Complete",
            "uuid": "ee36b2fa-0af4-4b31-aeed-56f18b26158b"
          },
          {
            "exit_uuid": "b41fdf01-eb81-4525-a113-9ef22e1dfa74",
            "name": "Expired",
            "uuid": "acb78524-568a-4959-9e56-0452cf33313b"
          }
        ],
        "default_category_uuid": "acb78524-568a-4959-9e56-0452cf33313b",
        "operand": "@child.run.status",
        "type": "switch"
      },
      "uuid": "a23adf12-69fe-4b9b-838c-a924e1848c49"
    },
    {
      "actions": [
        {
          "flow": {
            "name": "PLH - Content - Positive - Behave - Redirect - Timed intro",
            "uuid": "221299f8-2b0e-41d7-a05a-e8e82305a56b"
          },
          "type": "enter_flow",
          "uuid": "f153a2f1-0de7-45e6-83ac-91801885b265"
        }
      ],
      "exits": [
        {
          "destination_uuid": null,
          "uuid": "53182d1e-3deb-48bb-9841-b3d4e0cc5abc"
        },
        {
          "destination_uuid": "d0bc8187-3a70-409b-b12b-a1abe9ac76af",
          "uuid": "bb124fd4-0f95-4a3a-be08-1c528191d818"
        }
      ],
      "router": {
        "cases": [
          {
            "arguments": [
              "completed"
            ],
            "category_uuid": "9b42d6f2-a6aa-4b24-a1e6-6347789bc9e1",
            "type": "has_only_text",
            "uuid": "243ac6e7-6071-4781-87a2-41340b5a6ed8"
          },
          {
            "arguments": [
              "expired"
            ],
            "category_uuid": "ba00011b-c1e8-4cb3-9812-edd54f4e2123",
            "type": "has_only_text",
            "uuid": "6843bfb4-98cd-4c6a-861c-db6fbe160f3f"
          }
        ],
        "categories": [
          {
            "exit_uuid": "53182d1e-3deb-48bb-9841-b3d4e0cc5abc",
            "name": "Complete",
            "uuid": "9b42d6f2-a6aa-4b24-a1e6-6347789bc9e1"
          },
          {
            "exit_uuid": "bb124fd4-0f95-4a3a-be08-1c528191d818",
            "name": "Expired",
            "uuid": "ba00011b-c1e8-4cb3-9812-edd54f4e2123"
          }
        ],
        "default_category_uuid": "ba00011b-c1e8-4cb3-9812-edd54f4e2123",
        "operand": "@child.run.status",
        "type": "switch"
      },
      "uuid": "f6bbe8c7-b30f-4008-a9a7-ebc11c228046"
    },
    {
      "actions": [
        {
          "flow": {
            "name": "PLH - Content - Positive - Behave - ProblemSolving - Timed intro",
            "uuid": "24b6c98b-2aaa-4030-b5f7-9f5affa4dc04"
          },
          "type": "enter_flow",
          "uuid": "1f866c04-4ae5-4dbc-abc1-81e2046674e5"
        }
      ],
      "exits": [
        {
          "destination_uuid": null,
          "uuid": "c03060c7-32ef-44cd-a075-a9948d269814"
        },
        {
          "destination_uuid": "d0bc8187-3a70-409b-b12b-a1abe9ac76af",
          "uuid": "339df525-1e11-4997-ba67-8f0c510a299a"
        }
      ],
      "router": {
        "cases": [
          {
            "arguments": [
              "completed"
            ],
            "category_uuid": "8a0a2b68-58f7-4939-a39e-7d982f8b670a",
            "type": "has_only_text",
            "uuid": "d7c1fd71-bfb4-4ef2-b37f-f46687036d56"
          },
          {
            "arguments": [
              "expired"
            ],
            "category_uuid": "78780c9e-b05c-486f-94d5-76c66885d5f5",
            "type": "has_only_text",
            "uuid": "699b492c-d111-4aa2-a077-d413837e399f"
          }
        ],
        "categories": [
          {
            "exit_uuid": "c03060c7-32ef-44cd-a075-a9948d269814",
            "name": "Complete",
            "uuid": "8a0a2b68-58f7-4939-a39e-7d982f8b670a"
          },
          {
            "exit_uuid": "339df525-1e11-4997-ba67-8f0c510a299a",
            "name": "Expired",
            "uuid": "78780c9e-b05c-486f-94d5-76c66885d5f5"
          }
        ],
        "default_category_uuid": "78780c9e-b05c-486f-94d5-76c66885d5f5",
        "operand": "@child.run.status",
        "type": "switch"
      },
      "uuid": "2ab85e63-4e95-4dd8-bad3-e6aa4c76e81c"
    },
    {
      "actions": [],
      "exits": [
        {
          "destination_uuid": "f4ac1885-7de2-4197-af4b-5eb0995e7046",
          "uuid": "e395f854-dbb0-456a-91d6-33da9f10d1e5"
        },
        {
          "destination_uuid": "271c1218-7fc4-4991-bd06-2fb5d15219a8",
          "uuid": "d2878c81-c883-4d91-85ec-052bf4c2b71f"
        }
      ],
      "router": {
        "cases": [
          {
            "arguments": [
              "baby"
            ],
            "category_uuid": "1e677639-433b-4ef0-ad00-2ac5a8695d20",
            "type": "has_any_word",
            "uuid": "95520704-1a94-4eea-a711-ab657e5d842f"
          }
        ],
        "categories": [
          {
            "exit_uuid": "e395f854-dbb0-456a-91d6-33da9f10d1e5",
            "name": "Baby",
            "uuid": "1e677639-433b-4ef0-ad00-2ac5a8695d20"
          },
          {
            "exit_uuid": "d2878c81-c883-4d91-85ec-052bf4c2b71f",
            "name": "Other",
            "uuid": "a6ab39a8-8b8a-4eeb-b3c9-b8395d8aa7a1"
          }
        ],
        "default_category_uuid": "a6ab39a8-8b8a-4eeb-b3c9-b8395d8aa7a1",
        "operand": "@fields.age_group_for_tips",
        "type": "switch"
      },
      "uuid": "d22d7db9-9537-4617-9099-4a12eaa62566"
    },
    {
      "actions": [],
      "exits": [
        {
          "destination_uuid": "c1620dc8-2b6d-479e-bf9f-e5ed1e0529b3",
          "uuid": "c46762c0-ee56-484c-a414-713ff709f7ae"
        },
        {
          "destination_uuid": "35f05fba-0069-4755-be09-7a274ffe06c6",
          "uuid": "74082638-1b8e-4389-9dfc-1a64a433e54c"
        }
      ],
      "router": {
        "cases": [
          {
            "arguments": [
              "baby"
            ],
            "category_uuid": "e989ab05-e17a-4911-82c4-dc4d64d9f41c",
            "type": "has_any_word",
            "uuid": "5f6f12dd-bd23-4ef2-ac3d-b238a86a2fd7"
          }
        ],
        "categories": [
          {
            "exit_uuid": "c46762c0-ee56-484c-a414-713ff709f7ae",
            "name": "Baby",
            "uuid": "e989ab05-e17a-4911-82c4-dc4d64d9f41c"
          },
          {
            "exit_uuid": "74082638-1b8e-4389-9dfc-1a64a433e54c",
            "name": "Other",
            "uuid": "2e248d4e-6953-4961-8898-becf24e620d4"
          }
        ],
        "default_category_uuid": "2e248d4e-6953-4961-8898-becf24e620d4",
        "operand": "@fields.age_group_for_tips",
        "type": "switch"
      },
      "uuid": "540b0a25-c9a4-4521-8863-69d243f0a0d6"
    },
    {
      "actions": [
        {
          "flow": {
            "name": "PLH - Content - Positive - Behave - Consequences - Timed intro",
            "uuid": "7f995aa0-ae29-44e3-b0ad-cd38af7b589e"
          },
          "type": "enter_flow",
          "uuid": "d5fee5f5-7486-4cf0-9381-815a7e83c93c"
        }
      ],
      "exits": [
        {
          "destination_uuid": null,
          "uuid": "5bd1d2ef-b973-45c1-a744-e4b83ed1d3e1"
        },
        {
          "destination_uuid": "d0bc8187-3a70-409b-b12b-a1abe9ac76af",
          "uuid": "05d7950a-73a2-4d11-8b2b-b6b5ae1b9faa"
        }
      ],
      "router": {
        "cases": [
          {
            "arguments": [
              "completed"
            ],
            "category_uuid": "28760824-8d89-41c4-b62b-a5fc61113b95",
            "type": "has_only_text",
            "uuid": "3a2ce708-bcb7-48c9-83a5-f69ed86d0089"
          },
          {
            "arguments": [
              "expired"
            ],
            "category_uuid": "5a833830-feb1-4017-b829-e52cb44cd854",
            "type": "has_only_text",
            "uuid": "3321add0-560b-49b2-94ab-4013bfa21358"
          }
        ],
        "categories": [
          {
            "exit_uuid": "5bd1d2ef-b973-45c1-a744-e4b83ed1d3e1",
            "name": "Complete",
            "uuid": "28760824-8d89-41c4-b62b-a5fc61113b95"
          },
          {
            "exit_uuid": "05d7950a-73a2-4d11-8b2b-b6b5ae1b9faa",
            "name": "Expired",
            "uuid": "5a833830-feb1-4017-b829-e52cb44cd854"
          }
        ],
        "default_category_uuid": "5a833830-feb1-4017-b829-e52cb44cd854",
        "operand": "@child.run.status",
        "type": "switch"
      },
      "uuid": "3cdc6dbc-126b-4282-8ecf-aa9777477944"
    },
    {
      "actions": [
        {
          "flow": {
            "name": "PLH - Supportive - Share",
            "uuid": "8fc0dab6-c0f8-4d6c-bd8d-51944d9505fc"
          },
          "type": "enter_flow",
          "uuid": "900f6154-b044-4e4e-a962-241a4571ab09"
        }
      ],
      "exits": [
        {
          "destination_uuid": null,
          "uuid": "7b7cbb63-c598-452d-8af7-1ada1710c121"
        },
        {
          "destination_uuid": null,
          "uuid": "95659a06-3a1b-4759-8fdb-377738e5d366"
        }
      ],
      "router": {
        "cases": [
          {
            "arguments": [
              "completed"
            ],
            "category_uuid": "7988f19f-3a1e-4e06-b646-d9e7b31bc51d",
            "type": "has_only_text",
            "uuid": "3a07905b-d6ff-48f3-8579-345de7038ae4"
          },
          {
            "arguments": [
              "expired"
            ],
            "category_uuid": "5139f654-bfc7-4cc4-b274-1684ec3a3c0e",
            "type": "has_only_text",
            "uuid": "6b71ff25-ac94-460f-bfba-dbc001c1633c"
          }
        ],
        "categories": [
          {
            "exit_uuid": "7b7cbb63-c598-452d-8af7-1ada1710c121",
            "name": "Complete",
            "uuid": "7988f19f-3a1e-4e06-b646-d9e7b31bc51d"
          },
          {
            "exit_uuid": "95659a06-3a1b-4759-8fdb-377738e5d366",
            "name": "Expired",
            "uuid": "5139f654-bfc7-4cc4-b274-1684ec3a3c0e"
          }
        ],
        "default_category_uuid": "5139f654-bfc7-4cc4-b274-1684ec3a3c0e",
        "operand": "@child.run.status",
        "type": "switch"
      },
      "uuid": "e951b66f-9011-4a3c-a47a-5ef96f247135"
    },
    {
      "actions": [
        {
          "flow": {
            "name": "PLH - Content - Positive - Behave - Crying - Timed intro",
            "uuid": "375ae513-10e5-48ec-a148-0398b5bb4cc1"
          },
          "type": "enter_flow",
          "uuid": "26051886-f61d-4b7f-91ac-979f8dbcd83a"
        }
      ],
      "exits": [
        {
          "destination_uuid": null,
          "uuid": "f1fad711-f7f3-4a76-b5ac-713778f0c789"
        },
        {
          "destination_uuid": "d0bc8187-3a70-409b-b12b-a1abe9ac76af",
          "uuid": "877f76e0-0684-46a7-96ae-dfaff2a06938"
        }
      ],
      "router": {
        "cases": [
          {
            "arguments": [
              "completed"
            ],
            "category_uuid": "980f9433-d21a-48a0-8033-0978ced68ce2",
            "type": "has_only_text",
            "uuid": "967eb4fc-e38a-4629-9436-1908532d6f81"
          },
          {
            "arguments": [
              "expired"
            ],
            "category_uuid": "9cf31c52-3fc2-476b-9d93-38d42bfe31ed",
            "type": "has_only_text",
            "uuid": "35081c53-bfeb-4708-bb91-93fbe02e5dd9"
          }
        ],
        "categories": [
          {
            "exit_uuid": "f1fad711-f7f3-4a76-b5ac-713778f0c789",
            "name": "Complete",
            "uuid": "980f9433-d21a-48a0-8033-0978ced68ce2"
          },
          {
            "exit_uuid": "877f76e0-0684-46a7-96ae-dfaff2a06938",
            "name": "Expired",
            "uuid": "9cf31c52-3fc2-476b-9d93-38d42bfe31ed"
          }
        ],
        "default_category_uuid": "9cf31c52-3fc2-476b-9d93-38d42bfe31ed",
        "operand": "@child.run.status",
        "type": "switch"
      },
      "uuid": "f4ac1885-7de2-4197-af4b-5eb0995e7046"
    },
    {
      "uuid": "c1620dc8-2b6d-479e-bf9f-e5ed1e0529b3",
      "actions": [
        {
          "uuid": "36816696-6a40-4c0d-a646-b1e64e6dceb9",
          "type": "enter_flow",
          "flow": {
            "uuid": "8489d8d5-3dc8-463b-9e17-60d5a930e390",
            "name": "PLH - Supportive - Behave reminder"
          }
        }
      ],
      "router": {
        "type": "switch",
        "operand": "@child.run.status",
        "cases": [
          {
            "arguments": [
              "completed"
            ],
            "category_uuid": "a899b565-78f4-4027-9239-a7904451922a",
            "type": "has_only_text",
            "uuid": "505041ab-c0ae-4258-ae32-a186f72a17dc"
          },
          {
            "arguments": [
              "expired"
            ],
            "category_uuid": "ecce3d03-4842-4781-8df5-e7b380df8007",
            "type": "has_only_text",
            "uuid": "1044b7b3-de14-4035-91e9-31bfaabab20d"
          }
        ],
        "categories": [
          {
            "exit_uuid": "daa21987-df49-477b-b972-3739d4dfc7d3",
            "name": "Complete",
            "uuid": "a899b565-78f4-4027-9239-a7904451922a"
          },
          {
            "exit_uuid": "02eb7598-0a28-48d4-8c31-790559407f0f",
            "name": "Expired",
            "uuid": "ecce3d03-4842-4781-8df5-e7b380df8007"
          }
        ],
        "default_category_uuid": "ecce3d03-4842-4781-8df5-e7b380df8007"
      },
      "exits": [
        {
          "destination_uuid": null,
          "uuid": "daa21987-df49-477b-b972-3739d4dfc7d3"
        },
        {
          "destination_uuid": null,
          "uuid": "02eb7598-0a28-48d4-8c31-790559407f0f"
        }
      ]
    },
    {
      "actions": [
        {
          "flow": {
            "name": "PLH - Content - Positive - Behave - Ignore - Timed intro",
            "uuid": "b570fa21-cd75-421e-a222-b25c274d2204"
          },
          "type": "enter_flow",
          "uuid": "696538b7-c768-441f-9eba-544c380ddbbb"
        }
      ],
      "exits": [
        {
          "destination_uuid": null,
          "uuid": "aa8a4b89-4098-4d77-b655-b0cb4a8a844e"
        },
        {
          "destination_uuid": "d0bc8187-3a70-409b-b12b-a1abe9ac76af",
          "uuid": "956fc90d-c63c-48c4-8bc3-db3e09b04790"
        }
      ],
      "router": {
        "cases": [
          {
            "arguments": [
              "completed"
            ],
            "category_uuid": "c0a6bd3c-827c-4745-b584-4a679e30263d",
            "type": "has_only_text",
            "uuid": "33bd3313-c057-4e4f-9b22-50f46669ca79"
          },
          {
            "arguments": [
              "expired"
            ],
            "category_uuid": "a03ec29e-7e07-48b5-b163-b141063653ee",
            "type": "has_only_text",
            "uuid": "b12ed7b1-9a75-4ae0-bb52-0f8d5b067f09"
          }
        ],
        "categories": [
          {
            "exit_uuid": "aa8a4b89-4098-4d77-b655-b0cb4a8a844e",
            "name": "Complete",
            "uuid": "c0a6bd3c-827c-4745-b584-4a679e30263d"
          },
          {
            "exit_uuid": "956fc90d-c63c-48c4-8bc3-db3e09b04790",
            "name": "Expired",
            "uuid": "a03ec29e-7e07-48b5-b163-b141063653ee"
          }
        ],
        "default_category_uuid": "a03ec29e-7e07-48b5-b163-b141063653ee",
        "operand": "@child.run.status",
        "type": "switch"
      },
      "uuid": "b8a1f401-2d77-4689-ab65-98c058ac3a35"
    },
    {
      "actions": [
        {
          "flow": {
            "name": "PLH - Content - Positive - Online children - Timed intro",
            "uuid": "fb332ce0-4787-438a-b5a8-7727a9a15b28"
          },
          "type": "enter_flow",
          "uuid": "b2daa119-c466-4292-a3a9-bfeb0bfd0bdc"
        }
      ],
      "exits": [
        {
          "destination_uuid": null,
          "uuid": "606d2987-c4be-4d54-a311-35d307b8fc30"
        },
        {
          "destination_uuid": "d0bc8187-3a70-409b-b12b-a1abe9ac76af",
          "uuid": "7ca6253b-5fca-4232-a9f8-46ddfa516223"
        }
      ],
      "router": {
        "cases": [
          {
            "arguments": [
              "completed"
            ],
            "category_uuid": "bfe664ba-4803-4d5b-b5d5-b58a2d5c516b",
            "type": "has_only_text",
            "uuid": "fbd7867f-3b23-407f-8ce6-d9db4fbd25a6"
          },
          {
            "arguments": [
              "expired"
            ],
            "category_uuid": "e29f42a6-2847-4caf-9cd0-966ccf1bb028",
            "type": "has_only_text",
            "uuid": "e3126b06-269e-499f-87de-84e5b7e7df22"
          }
        ],
        "categories": [
          {
            "exit_uuid": "606d2987-c4be-4d54-a311-35d307b8fc30",
            "name": "Complete",
            "uuid": "bfe664ba-4803-4d5b-b5d5-b58a2d5c516b"
          },
          {
            "exit_uuid": "7ca6253b-5fca-4232-a9f8-46ddfa516223",
            "name": "Expired",
            "uuid": "e29f42a6-2847-4caf-9cd0-966ccf1bb028"
          }
        ],
        "default_category_uuid": "e29f42a6-2847-4caf-9cd0-966ccf1bb028",
        "operand": "@child.run.status",
        "type": "switch"
      },
      "uuid": "271c1218-7fc4-4991-bd06-2fb5d15219a8"
    },
    {
      "actions": [
        {
          "flow": {
            "name": "PLH - Content - Positive - Behave - Emotion - Timed intro",
            "uuid": "46d1dfc6-ec21-4df5-942c-8813b26560e7"
          },
          "type": "enter_flow",
          "uuid": "092b2c66-0055-4337-b039-0c307c2d7d54"
        }
      ],
      "exits": [
        {
          "destination_uuid": null,
          "uuid": "957c2b0c-1279-46a9-a0b3-75759986a7c2"
        },
        {
          "destination_uuid": "d0bc8187-3a70-409b-b12b-a1abe9ac76af",
          "uuid": "ea0d1cca-bfa2-441b-b98c-99de37b86267"
        }
      ],
      "router": {
        "cases": [
          {
            "arguments": [
              "completed"
            ],
            "category_uuid": "2da26bf0-667f-4338-804f-5d33be890d04",
            "type": "has_only_text",
            "uuid": "4db80713-d546-4fca-8d15-7e47903e2c33"
          },
          {
            "arguments": [
              "expired"
            ],
            "category_uuid": "9d939e54-68e0-48e4-b6a0-4004b4dc7a04",
            "type": "has_only_text",
            "uuid": "0f3ccf02-f584-4ece-a47f-09625f4933f1"
          }
        ],
        "categories": [
          {
            "exit_uuid": "957c2b0c-1279-46a9-a0b3-75759986a7c2",
            "name": "Complete",
            "uuid": "2da26bf0-667f-4338-804f-5d33be890d04"
          },
          {
            "exit_uuid": "ea0d1cca-bfa2-441b-b98c-99de37b86267",
            "name": "Expired",
            "uuid": "9d939e54-68e0-48e4-b6a0-4004b4dc7a04"
          }
        ],
        "default_category_uuid": "9d939e54-68e0-48e4-b6a0-4004b4dc7a04",
        "operand": "@child.run.status",
        "type": "switch"
      },
      "uuid": "35f05fba-0069-4755-be09-7a274ffe06c6"
    },
    {
      "actions": [],
      "exits": [
        {
          "destination_uuid": "7a2088b1-74dd-4431-ace7-5a7f1ed67b05",
          "uuid": "6ea7876b-c062-414a-a377-b08dd501f9f1"
        },
        {
          "destination_uuid": "37d06de9-9716-423f-a511-c70418af2f21",
          "uuid": "decb2fc6-a3c4-40ab-8253-ef45e27a98d8"
        }
      ],
      "router": {
        "cases": [
          {
            "arguments": [
              "teen"
            ],
            "category_uuid": "7d66fdf5-7503-48a9-901d-f42cf306f59b",
            "type": "has_any_word",
            "uuid": "6d68f569-37f1-4154-a47d-fab8ced3cf32"
          }
        ],
        "categories": [
          {
            "exit_uuid": "6ea7876b-c062-414a-a377-b08dd501f9f1",
            "name": "Teen",
            "uuid": "7d66fdf5-7503-48a9-901d-f42cf306f59b"
          },
          {
            "exit_uuid": "decb2fc6-a3c4-40ab-8253-ef45e27a98d8",
            "name": "Other",
            "uuid": "e66cde5c-c172-4a2d-bed6-c5cf4fc0ada2"
          }
        ],
        "default_category_uuid": "e66cde5c-c172-4a2d-bed6-c5cf4fc0ada2",
        "operand": "@fields.age_group_for_tips",
        "type": "switch"
      },
      "uuid": "b050ae77-dd48-4ce6-8fcc-8e187aae0b45"
    },
    {
      "actions": [
        {
          "category": "",
          "name": "main content",
          "type": "set_run_result",
          "uuid": "ae5f0bf5-a983-42e6-acaa-5288fefaa9be",
          "value": "no"
        }
      ],
      "exits": [
        {
          "destination_uuid": null,
          "uuid": "a2639384-a48b-48b0-87e3-30b7998ac913"
        }
      ],
      "uuid": "af9859b1-7e91-47bc-b460-14b7197c39f4"
    },
    {
      "uuid": "4207d3fc-d207-4f85-99a9-95e457604489",
      "actions": [],
      "router": {
        "type": "switch",
        "default_category_uuid": "8787ee88-ad85-452c-802a-4e4b54fa3850",
        "cases": [
          {
            "arguments": [
              "17"
            ],
            "type": "has_any_word",
            "uuid": "36a14816-c7eb-4c37-8a1a-7afe234976f6",
            "category_uuid": "cd14831f-3772-46d7-bbf9-322f37239a44"
          },
          {
            "arguments": [
              "18"
            ],
            "type": "has_any_word",
            "uuid": "03a6abfd-f913-41ef-96dc-8acf7c48ac1a",
            "category_uuid": "281d784f-4648-48f9-bff4-6a1a960b79dc"
          },
          {
            "arguments": [
              "20"
            ],
            "type": "has_any_word",
            "uuid": "adbe5239-b3b6-4b32-b75a-7ebfd3f69d16",
            "category_uuid": "7d7e21ab-0411-4231-99b9-bfd2aead8f91"
          },
          {
            "arguments": [
              "21"
            ],
            "type": "has_any_word",
            "uuid": "d12fcd62-e490-4f0e-928a-8394aa166bef",
            "category_uuid": "d02f148b-18ea-4b96-8dd7-979e1029f383"
          }
        ],
        "categories": [
          {
            "exit_uuid": "432d24da-98af-4818-9eba-206e35391d2a",
            "name": "17",
            "uuid": "cd14831f-3772-46d7-bbf9-322f37239a44"
          },
          {
            "uuid": "281d784f-4648-48f9-bff4-6a1a960b79dc",
            "name": "18",
            "exit_uuid": "762b5534-9302-42ca-b7e6-688b6572f7ed"
          },
          {
            "exit_uuid": "2eb8eacd-df7e-4a4c-9b2b-8580fa6f5db2",
            "name": "20",
            "uuid": "7d7e21ab-0411-4231-99b9-bfd2aead8f91"
          },
          {
            "uuid": "d02f148b-18ea-4b96-8dd7-979e1029f383",
            "name": "21",
            "exit_uuid": "0bba09fd-78cc-4e66-b8f2-761f50ec0fbe"
          },
          {
            "exit_uuid": "a9c8cf18-922c-4992-838a-f2fc83b65813",
            "name": "Other",
            "uuid": "8787ee88-ad85-452c-802a-4e4b54fa3850"
          }
        ],
        "operand": "@fields.next_tip_main"
      },
      "exits": [
        {
          "destination_uuid": "b050ae77-dd48-4ce6-8fcc-8e187aae0b45",
          "uuid": "432d24da-98af-4818-9eba-206e35391d2a"
        },
        {
          "uuid": "762b5534-9302-42ca-b7e6-688b6572f7ed",
          "destination_uuid": "93b8d31b-5309-4470-83d4-167209e64ca8"
        },
        {
          "destination_uuid": "d0a71643-2a3e-4d77-b021-d2f60f408837",
          "uuid": "2eb8eacd-df7e-4a4c-9b2b-8580fa6f5db2"
        },
        {
          "uuid": "0bba09fd-78cc-4e66-b8f2-761f50ec0fbe",
          "destination_uuid": "70805de3-56fb-42a9-a115-6b6f074176a6"
        },
        {
          "destination_uuid": "af9859b1-7e91-47bc-b460-14b7197c39f4",
          "uuid": "a9c8cf18-922c-4992-838a-f2fc83b65813"
        }
      ]
    },
    {
      "actions": [
        {
          "flow": {
            "name": "PLH - Content - Positive - Behave - Crisis - Timed intro",
            "uuid": "834191e5-450d-4af3-b192-4350e4a7d457"
          },
          "type": "enter_flow",
          "uuid": "fb58c4d6-fe76-4408-9bae-b2c980a90231"
        }
      ],
      "exits": [
        {
          "destination_uuid": null,
          "uuid": "fc2e70c4-78c1-4178-929c-68a3c353b8b3"
        },
        {
          "destination_uuid": "d0bc8187-3a70-409b-b12b-a1abe9ac76af",
          "uuid": "3f8f9d04-7232-4c4c-8a8b-d4c867109cda"
        }
      ],
      "router": {
        "cases": [
          {
            "arguments": [
              "completed"
            ],
            "category_uuid": "deb61b82-1dfe-4d18-8551-244173ab9a72",
            "type": "has_only_text",
            "uuid": "4b518aee-6f28-4cd9-906b-5f410f5551a9"
          },
          {
            "arguments": [
              "expired"
            ],
            "category_uuid": "053542d0-d490-403d-a827-703439a91813",
            "type": "has_only_text",
            "uuid": "b4371d43-6b7d-4322-bf09-3cc891f41245"
          }
        ],
        "categories": [
          {
            "exit_uuid": "fc2e70c4-78c1-4178-929c-68a3c353b8b3",
            "name": "Complete",
            "uuid": "deb61b82-1dfe-4d18-8551-244173ab9a72"
          },
          {
            "exit_uuid": "3f8f9d04-7232-4c4c-8a8b-d4c867109cda",
            "name": "Expired",
            "uuid": "053542d0-d490-403d-a827-703439a91813"
          }
        ],
        "default_category_uuid": "053542d0-d490-403d-a827-703439a91813",
        "operand": "@child.run.status",
        "type": "switch"
      },
      "uuid": "7a2088b1-74dd-4431-ace7-5a7f1ed67b05"
    },
    {
      "actions": [],
      "exits": [
        {
          "destination_uuid": "3042bac4-f5d3-4508-8c7f-9ab47af7c99a",
          "uuid": "5e9a6e4f-efe7-4914-af59-ea8d88502c34"
        },
        {
          "destination_uuid": "db7afc44-fa0f-4369-95a9-236a228f7923",
          "uuid": "ac8abcea-a5b8-42ed-9fbd-0e30a1882258"
        }
      ],
      "router": {
        "cases": [
          {
            "arguments": [
              "baby"
            ],
            "category_uuid": "abb633ab-2c20-4a2b-9be0-fb7ec7b2f7ba",
            "type": "has_any_word",
            "uuid": "33fc1953-6745-4f26-9123-94f0c89c465b"
          }
        ],
        "categories": [
          {
            "exit_uuid": "5e9a6e4f-efe7-4914-af59-ea8d88502c34",
            "name": "Baby",
            "uuid": "abb633ab-2c20-4a2b-9be0-fb7ec7b2f7ba"
          },
          {
            "exit_uuid": "ac8abcea-a5b8-42ed-9fbd-0e30a1882258",
            "name": "Other",
            "uuid": "4861f5bf-2375-49fc-9ced-43629a628a30"
          }
        ],
        "default_category_uuid": "4861f5bf-2375-49fc-9ced-43629a628a30",
        "operand": "@fields.age_group_for_tips",
        "type": "switch"
      },
      "uuid": "d0a71643-2a3e-4d77-b021-d2f60f408837"
    },
    {
      "actions": [
        {
          "flow": {
            "name": "PLH - Content - Positive - Safe or unsafe touch - Timed intro",
            "uuid": "7debb382-39f6-49c0-9b2e-5da96bcdb277"
          },
          "type": "enter_flow",
          "uuid": "e18db35f-2008-43c1-b854-0406b0c7f51d"
        }
      ],
      "exits": [
        {
          "destination_uuid": null,
          "uuid": "b89ef2ee-84ae-41ca-9527-4b8c5c04f2cd"
        },
        {
          "destination_uuid": "d0bc8187-3a70-409b-b12b-a1abe9ac76af",
          "uuid": "1ce58ec3-cefb-4c35-b3aa-5603f07b0aa3"
        }
      ],
      "router": {
        "cases": [
          {
            "arguments": [
              "completed"
            ],
            "category_uuid": "09b0be1b-6e6c-457c-930e-69ee4a550f9c",
            "type": "has_only_text",
            "uuid": "91b67727-6060-4b03-9ea3-d42c233ef6a7"
          },
          {
            "arguments": [
              "expired"
            ],
            "category_uuid": "f970226e-b864-4ddc-b90c-f2c16538fe33",
            "type": "has_only_text",
            "uuid": "61dda23b-aa6f-413f-b35a-b78c1078fa9f"
          }
        ],
        "categories": [
          {
            "exit_uuid": "b89ef2ee-84ae-41ca-9527-4b8c5c04f2cd",
            "name": "Complete",
            "uuid": "09b0be1b-6e6c-457c-930e-69ee4a550f9c"
          },
          {
            "exit_uuid": "1ce58ec3-cefb-4c35-b3aa-5603f07b0aa3",
            "name": "Expired",
            "uuid": "f970226e-b864-4ddc-b90c-f2c16538fe33"
          }
        ],
        "default_category_uuid": "f970226e-b864-4ddc-b90c-f2c16538fe33",
        "operand": "@child.run.status",
        "type": "switch"
      },
      "uuid": "37d06de9-9716-423f-a511-c70418af2f21"
    },
    {
      "actions": [
        {
          "flow": {
            "name": "PLH - Content - Positive - Budget with children - Timed intro",
            "uuid": "82a70d44-3235-4748-83fd-d5fa929a4766"
          },
          "type": "enter_flow",
          "uuid": "a651f647-6b16-46e4-84e8-43aa2aed1e37"
        }
      ],
      "exits": [
        {
          "destination_uuid": null,
          "uuid": "643329a9-822b-4827-9dd4-9e82adf3b74c"
        },
        {
          "destination_uuid": "d0bc8187-3a70-409b-b12b-a1abe9ac76af",
          "uuid": "7ee97e3f-9230-4ac2-a5ca-e85a9428ba6c"
        }
      ],
      "router": {
        "cases": [
          {
            "arguments": [
              "completed"
            ],
            "category_uuid": "260061b3-1504-4ca6-8edd-9cb8a5ad3614",
            "type": "has_only_text",
            "uuid": "40d93fa2-e06e-4673-be16-ddff17e1161a"
          },
          {
            "arguments": [
              "expired"
            ],
            "category_uuid": "779b15fe-6b07-475f-938a-85bb12823203",
            "type": "has_only_text",
            "uuid": "f356cecf-d2aa-409d-9834-ef84f5048a00"
          }
        ],
        "categories": [
          {
            "exit_uuid": "643329a9-822b-4827-9dd4-9e82adf3b74c",
            "name": "Complete",
            "uuid": "260061b3-1504-4ca6-8edd-9cb8a5ad3614"
          },
          {
            "exit_uuid": "7ee97e3f-9230-4ac2-a5ca-e85a9428ba6c",
            "name": "Expired",
            "uuid": "779b15fe-6b07-475f-938a-85bb12823203"
          }
        ],
        "default_category_uuid": "779b15fe-6b07-475f-938a-85bb12823203",
        "operand": "@child.run.status",
        "type": "switch"
      },
      "uuid": "db7afc44-fa0f-4369-95a9-236a228f7923"
    },
    {
      "actions": [
        {
          "flow": {
            "name": "PLH - Content - Positive - Budget adults - Timed intro",
            "uuid": "66e68eea-54bf-4390-89c0-a9be9baa3bd4"
          },
          "type": "enter_flow",
          "uuid": "ce9c7568-a45e-4dc3-9acc-0dedbf814cad"
        }
      ],
      "exits": [
        {
          "destination_uuid": null,
          "uuid": "593df222-00f2-41fd-a081-1cfbb31c6a76"
        },
        {
          "destination_uuid": "d0bc8187-3a70-409b-b12b-a1abe9ac76af",
          "uuid": "e329352a-2a6c-4072-b0ed-71a186928741"
        }
      ],
      "router": {
        "cases": [
          {
            "arguments": [
              "completed"
            ],
            "category_uuid": "818c0000-a584-427b-99c1-52dde0e64fea",
            "type": "has_only_text",
            "uuid": "f50ba592-8de3-4413-acf0-aa6cc0d4a59e"
          },
          {
            "arguments": [
              "expired"
            ],
            "category_uuid": "7b6cee79-2596-4992-9c48-787d09b10249",
            "type": "has_only_text",
            "uuid": "f7a5999d-4abc-4d79-a44e-5da013a9280d"
          }
        ],
        "categories": [
          {
            "exit_uuid": "593df222-00f2-41fd-a081-1cfbb31c6a76",
            "name": "Complete",
            "uuid": "818c0000-a584-427b-99c1-52dde0e64fea"
          },
          {
            "exit_uuid": "e329352a-2a6c-4072-b0ed-71a186928741",
            "name": "Expired",
            "uuid": "7b6cee79-2596-4992-9c48-787d09b10249"
          }
        ],
        "default_category_uuid": "7b6cee79-2596-4992-9c48-787d09b10249",
        "operand": "@child.run.status",
        "type": "switch"
      },
      "uuid": "3042bac4-f5d3-4508-8c7f-9ab47af7c99a"
    },
    {
      "actions": [
        {
          "flow": {
            "name": "PLH - Content - Positive - CheckIn - Routines",
            "uuid": "487e80f2-1639-44ee-9823-bec23f5deb79"
          },
          "type": "enter_flow",
          "uuid": "be7e9c5e-73fa-4d15-a958-b02a095eb570"
        }
      ],
      "exits": [
        {
          "destination_uuid": null,
          "uuid": "e393b4de-91e1-45c3-89e5-dd6ceab15473"
        },
        {
          "destination_uuid": null,
          "uuid": "c7fbec5f-ec81-45a2-abd2-585a9e7d196d"
        }
      ],
      "router": {
        "cases": [
          {
            "arguments": [
              "completed"
            ],
            "category_uuid": "4ee08683-2f70-433c-a291-eee7db8cfd01",
            "type": "has_only_text",
            "uuid": "72576fb9-eefc-47b9-9fed-72f29f2ac21e"
          },
          {
            "arguments": [
              "expired"
            ],
            "category_uuid": "355c4992-0b83-4c40-b145-e617d966c2eb",
            "type": "has_only_text",
            "uuid": "23e3c527-9e3a-4076-ac6e-fcb1d5c5d72b"
          }
        ],
        "categories": [
          {
            "exit_uuid": "e393b4de-91e1-45c3-89e5-dd6ceab15473",
            "name": "Complete",
            "uuid": "4ee08683-2f70-433c-a291-eee7db8cfd01"
          },
          {
            "exit_uuid": "c7fbec5f-ec81-45a2-abd2-585a9e7d196d",
            "name": "Expired",
            "uuid": "355c4992-0b83-4c40-b145-e617d966c2eb"
          }
        ],
        "default_category_uuid": "355c4992-0b83-4c40-b145-e617d966c2eb",
        "operand": "@child.run.status",
        "type": "switch"
      },
      "uuid": "70805de3-56fb-42a9-a115-6b6f074176a6"
    },
    {
      "uuid": "93b8d31b-5309-4470-83d4-167209e64ca8",
      "actions": [
        {
          "uuid": "70c39444-467b-4850-a218-6e2198c7cd04",
          "type": "enter_flow",
          "flow": {
            "uuid": "ea204181-4853-488e-bba1-f7690fd04c66",
            "name": "PLH - Content - Positive - Family - Timed intro"
          }
        }
      ],
      "router": {
        "type": "switch",
        "operand": "@child.run.status",
        "cases": [
          {
            "uuid": "cb12f95c-b2f0-445c-8cab-3f349e8d47ab",
            "type": "has_only_text",
            "arguments": [
              "completed"
            ],
            "category_uuid": "2b07a448-d9a8-4c09-bca1-5eb8e0083211"
          },
          {
            "uuid": "a0f8a3d9-0f24-4df7-ad8a-98faf3761880",
            "arguments": [
              "expired"
            ],
            "type": "has_only_text",
            "category_uuid": "576eacef-fc08-4aa3-8561-f5c2b622e464"
          }
        ],
        "categories": [
          {
            "uuid": "2b07a448-d9a8-4c09-bca1-5eb8e0083211",
            "name": "Complete",
            "exit_uuid": "51c3f6c4-835e-47a0-a9e7-2d5125b66fbb"
          },
          {
            "uuid": "576eacef-fc08-4aa3-8561-f5c2b622e464",
            "name": "Expired",
            "exit_uuid": "7fd54aa1-d332-49be-8ebe-2f89516fc03d"
          }
        ],
        "default_category_uuid": "576eacef-fc08-4aa3-8561-f5c2b622e464"
      },
      "exits": [
        {
          "uuid": "51c3f6c4-835e-47a0-a9e7-2d5125b66fbb",
          "destination_uuid": null
        },
        {
          "uuid": "7fd54aa1-d332-49be-8ebe-2f89516fc03d",
          "destination_uuid": "d0bc8187-3a70-409b-b12b-a1abe9ac76af"
        }
      ]
    },
    {
      "actions": [
        {
          "flow": {
            "name": "PLH - Content - Positive - CheckIn - Routines with song ",
            "uuid": "6896d7f7-7ac2-4df1-8d99-d5bbf6837134"
          },
          "type": "enter_flow",
          "uuid": "a96b62d8-f639-40c9-80bb-cf6c99b803db"
        }
      ],
      "exits": [
        {
          "destination_uuid": null,
          "uuid": "982464d9-f32c-4150-b191-ecb0be44a0e7"
        },
        {
          "destination_uuid": null,
          "uuid": "5296b0c2-94b0-4dff-8d99-5d234642aff3"
        }
      ],
      "router": {
        "cases": [
          {
            "arguments": [
              "completed"
            ],
            "category_uuid": "42a64b36-45eb-4194-ad32-c7e9538c3a9b",
            "type": "has_only_text",
            "uuid": "cec6af53-33c1-4d1c-bae2-fe48c1a265a9"
          },
          {
            "arguments": [
              "expired"
            ],
            "category_uuid": "2f255d95-dc19-49e7-b4f5-6d4d238c0cf6",
            "type": "has_only_text",
            "uuid": "a4f7f451-ed03-480b-9b94-34dab939d7f8"
          }
        ],
        "categories": [
          {
            "exit_uuid": "982464d9-f32c-4150-b191-ecb0be44a0e7",
            "name": "Complete",
            "uuid": "42a64b36-45eb-4194-ad32-c7e9538c3a9b"
          },
          {
            "exit_uuid": "5296b0c2-94b0-4dff-8d99-5d234642aff3",
            "name": "Expired",
            "uuid": "2f255d95-dc19-49e7-b4f5-6d4d238c0cf6"
          }
        ],
        "default_category_uuid": "2f255d95-dc19-49e7-b4f5-6d4d238c0cf6",
        "operand": "@child.run.status",
        "type": "switch"
      },
      "uuid": "98a20f9c-0c09-4afc-8f8a-2bee3c264e6f"
    }
  ],
  "spec_version": "13.1.0",
  "type": "messaging",
  "uuid": "e6b22cd8-fd8d-4fc9-bba3-fc5bc369aee1",
  "revision": 55
}