{
  "_ui": {
    "nodes": {
      "0af05335-7e24-425e-a7f1-e66e8d1621eb": {
        "position": {
          "left": 940,
          "top": 3300
        },
        "type": "execute_actions"
      },
      "150d3ac7-46f5-4325-90cc-dbafbc94caf8": {
        "config": {},
        "position": {
          "left": 580,
          "top": 2020
        },
        "type": "split_by_subflow"
      },
      "26719023-7df9-4c61-b0bd-181634b277f9": {
        "position": {
          "left": 780,
          "top": 540
        },
        "type": "execute_actions"
      },
      "2705691c-e6bd-43ae-980f-2b4109b040cd": {
        "config": {},
        "position": {
          "left": 60,
          "top": 2360
        },
        "type": "split_by_subflow"
      },
      "27b563aa-75a5-45a0-930c-43a8796fbcbf": {
        "position": {
          "left": 640,
          "top": 3160
        },
        "type": "execute_actions"
      },
      "3004d9fc-38cf-439e-b6c2-8bd59d714186": {
        "position": {
          "left": 1000,
          "top": 1520
        },
        "type": "execute_actions"
      },
      "38b6223a-fd99-4b96-bedd-cf6ec6dcf44b": {
        "config": {},
        "position": {
          "left": 600,
          "top": 1760
        },
        "type": "split_by_subflow"
      },
      "40ce064e-705d-4b2e-84bb-bae338c45509": {
        "config": {},
        "position": {
          "left": 620,
          "top": 2160
        },
        "type": "split_by_subflow"
      },
      "445bd23e-b901-457e-ada7-2025a126eda6": {
        "config": {},
        "position": {
          "left": 760,
          "top": 2600
        },
        "type": "split_by_subflow"
      },
      "50672de5-38bd-47c0-b63f-699be3126691": {
        "position": {
          "left": 540,
          "top": 160
        },
        "type": "execute_actions"
      },
      "57d1db55-6919-46d3-8958-b60301261eec": {
        "config": {},
        "position": {
          "left": 700,
          "top": 2880
        },
        "type": "split_by_subflow"
      },
      "5f90c4cc-f920-49e7-a459-f274980d6026": {
        "config": {
          "cases": {}
        },
        "position": {
          "left": 120,
          "top": 1020
        },
        "type": "wait_for_response"
      },
      "60859110-5194-4a11-b479-e2d7f4ad5f15": {
        "config": {
          "cases": {},
          "operand": {
            "id": "selected_skill",
            "name": "selected skill",
            "type": "result"
          }
        },
        "position": {
          "left": 720,
          "top": 1160
        },
        "type": "split_by_run_result"
      },
      "60ede010-5e00-4a6a-b896-d74ac839625c": {
        "config": {},
        "position": {
          "left": 620,
          "top": 2740
        },
        "type": "split_by_subflow"
      },
      "6a542ecf-83a0-4db1-b744-3f4e53512cf0": {
        "config": {},
        "position": {
          "left": 380,
          "top": 2460
        },
        "type": "split_by_subflow"
      },
      "6ab88684-82fc-4ad3-9568-c0bc5112c355": {
        "config": {},
        "position": {
          "left": 600,
          "top": 3440
        },
        "type": "split_by_subflow"
      },
      "6cab33c0-f168-46cf-899b-2fc2fe9333d6": {
        "position": {
          "left": 1120,
          "top": 380
        },
        "type": "execute_actions"
      },
      "703177b3-da7b-4d32-b131-c8715be98d43": {
        "config": {
          "cases": {},
          "operand": {
            "id": "incomplete_toolkit",
            "name": "incomplete toolkit",
            "type": "field"
          }
        },
        "position": {
          "left": 840,
          "top": 360
        },
        "type": "split_by_contact_field"
      },
      "74261f31-b91b-410a-b96f-8ec8ab1469df": {
        "config": {},
        "position": {
          "left": 600,
          "top": 1620
        },
        "type": "split_by_subflow"
      },
      "77118c51-ade8-400c-8bc8-ca01e4cc40cd": {
        "position": {
          "left": 1180,
          "top": 1180
        },
        "type": "execute_actions"
      },
      "817c059a-b5f3-46c8-b184-10ea3223c418": {
        "config": {
          "cases": {}
        },
        "position": {
          "left": 580,
          "top": 3300
        },
        "type": "wait_for_response"
      },
      "828e7627-5cdb-4477-9429-ffae26840966": {
        "config": {},
        "position": {
          "left": 60,
          "top": 2200
        },
        "type": "split_by_subflow"
      },
      "84e69394-7cc9-46fe-812e-7be7c6317cad": {
        "position": {
          "left": 880,
          "top": 220
        },
        "type": "execute_actions"
      },
      "86855813-cacf-4ce2-a909-2a9d76593d55": {
        "position": {
          "left": 140,
          "top": 700
        },
        "type": "execute_actions"
      },
      "8ae5fd77-15f7-4893-b323-b5d2be6c7353": {
        "config": {
          "cases": {},
          "operand": {
            "id": "selected_skill",
            "name": "selected skill",
            "type": "result"
          }
        },
        "position": {
          "left": 40,
          "top": 1160
        },
        "type": "split_by_run_result"
      },
      "90614677-7caa-49c0-a585-b972634acd31": {
        "config": {
          "cases": {}
        },
        "position": {
          "left": 500,
          "top": 380
        },
        "type": "wait_for_response"
      },
      "96f73aef-7c35-4302-ab0e-15ae2d1c0ddf": {
        "config": {},
        "position": {
          "left": 340,
          "top": 1660
        },
        "type": "split_by_subflow"
      },
      "9e3f5e64-4f1b-44b9-b670-ec7a5256f98e": {
        "position": {
          "left": 520,
          "top": 0
        },
        "type": "execute_actions"
      },
      "a711e9af-2dc3-4f3a-ac6e-1a487b49a5ee": {
        "config": {
          "cases": {},
          "operand": {
            "id": "toolkit",
            "name": "toolkit",
            "type": "field"
          }
        },
        "position": {
          "left": 440,
          "top": 520
        },
        "type": "split_by_contact_field"
      },
      "b04258f3-405f-4d25-9627-7873147a5f8d": {
        "config": {},
        "position": {
          "left": 1020,
          "top": 2280
        },
        "type": "split_by_subflow"
      },
      "b687cf52-17cc-47a1-b5a9-22d690ec7072": {
        "config": {
          "cases": {},
          "operand": {
            "id": "index_of_skill",
            "name": "index of skill",
            "type": "result"
          }
        },
        "position": {
          "left": 160,
          "top": 3020
        },
        "type": "split_by_run_result"
      },
      "b9abbfbf-6fc2-4a4b-9d7c-5cafec3aae06": {
        "config": {},
        "position": {
          "left": 920,
          "top": 1900
        },
        "type": "split_by_subflow"
      },
      "bb49efe8-5184-4216-85d3-87b08206c37c": {
        "position": {
          "left": 80,
          "top": 300
        },
        "type": "execute_actions"
      },
      "bc5c0660-aa61-41d1-9257-26b7f0f66e09": {
        "config": {},
        "position": {
          "left": 460,
          "top": 800
        },
        "type": "split_by_subflow"
      },
      "bdfd477a-a78e-4164-9593-7742aa7d9ee4": {
        "config": {},
        "position": {
          "left": 1160,
          "top": 600
        },
        "type": "split_by_subflow"
      },
      "c5f33880-b3b7-40b1-9c8d-1f11ed603ea4": {
        "config": {},
        "position": {
          "left": 40,
          "top": 1640
        },
        "type": "split_by_subflow"
      },
      "c77bfe10-c6a9-47d2-bb52-9037b4c41cf5": {
        "position": {
          "left": 560,
          "top": 1320
        },
        "type": "execute_actions"
      },
      "d5a0a460-3760-4f6e-ac00-c363cf585b27": {
        "config": {
          "cases": {}
        },
        "position": {
          "left": 700,
          "top": 1020
        },
        "type": "wait_for_response"
      },
      "d8608c2f-3c89-4fe8-a4af-84ffb923ec61": {
        "config": {},
        "position": {
          "left": 400,
          "top": 2620
        },
        "type": "split_by_subflow"
      },
      "d9372265-a1b4-4308-a37a-922a4ba88f40": {
        "config": {},
        "position": {
          "left": 140,
          "top": 540
        },
        "type": "split_by_subflow"
      },
      "db6ded62-b361-4764-92b5-ca57d18b57b6": {
        "position": {
          "left": 460,
          "top": 640
        },
        "type": "execute_actions"
      },
      "e1382546-aed0-4329-af6c-ccdcd43aba27": {
        "config": {},
        "position": {
          "left": 620,
          "top": 2300
        },
        "type": "split_by_subflow"
      },
      "e1c7d119-c381-4c95-8e34-e4fe550576f4": {
        "position": {
          "left": 460,
          "top": 940
        },
        "type": "execute_actions"
      },
      "e56b17f8-5ed4-4f1c-9852-990fefd704db": {
        "config": {},
        "position": {
          "left": 20,
          "top": 1920
        },
        "type": "split_by_subflow"
      },
      "e99c7604-5d60-4295-9d53-6c3eabc3cb90": {
        "config": {},
        "position": {
          "left": 60,
          "top": 1780
        },
        "type": "split_by_subflow"
      },
      "ea9cfa3c-84b3-4282-be6e-7b0a15f24aa2": {
        "config": {},
        "position": {
          "left": 620,
          "top": 2460
        },
        "type": "split_by_subflow"
      },
      "edab3dd3-0bf5-464b-b4ec-fcd14f98cc1d": {
        "config": {},
        "position": {
          "left": 340,
          "top": 2020
        },
        "type": "split_by_subflow"
      },
      "f2242e16-ef6e-441e-b7e8-8adfbcf7d741": {
        "config": {},
        "position": {
          "left": 360,
          "top": 2320
        },
        "type": "split_by_subflow"
      },
      "f40feb2f-2b4d-4a82-934a-6ec845662dff": {
        "config": {},
        "position": {
          "left": 940,
          "top": 2460
        },
        "type": "split_by_subflow"
      },
      "f5ec8299-a71b-46d8-a1af-329e1b019d03": {
        "config": {},
        "position": {
          "left": 340,
          "top": 2160
        },
        "type": "split_by_subflow"
      },
      "fd5f6732-40f8-44c5-9e70-b1e5593fc3c9": {
        "config": {},
        "position": {
          "left": 60,
          "top": 2060
        },
        "type": "split_by_subflow"
      }
    },
    "stickies": {}
  },
  "expire_after_minutes": 60,
  "ignore_triggers": true,
  "language": "eng",
  "localization": {},
  "metadata": {
    "revision": 20
  },
  "name": "PLH - Help - Access toolkit",
  "nodes": [
    {
      "actions": [
        {
          "field": {
            "key": "last_interaction",
            "name": "last interaction"
          },
          "type": "set_contact_field",
          "uuid": "b317c580-f838-4037-a414-8b9410584c59",
          "value": "@(now())"
        },
        {
          "field": {
            "key": "from_theme",
            "name": "from theme"
          },
          "type": "set_contact_field",
          "uuid": "45c08ede-f5a4-44aa-9589-abeb8c5d398b",
          "value": "no"
        }
      ],
      "exits": [
        {
          "destination_uuid": "50672de5-38bd-47c0-b63f-699be3126691",
          "uuid": "1b06b620-d1b4-41c9-baf9-45ca1bf2263e"
        }
      ],
      "uuid": "9e3f5e64-4f1b-44b9-b670-ec7a5256f98e"
    },
    {
      "actions": [
        {
          "attachments": [],
          "quick_replies": [
            "Skills in toolkit",
            "Incomplete skills"
          ],
          "text": "Which parenting topics would you like to revisit?\n\nType \"back\" if you want to go back to the Help menu.",
          "type": "send_msg",
          "uuid": "748584d6-8d2d-47bb-9518-a0409acc7a95"
        }
      ],
      "exits": [
        {
          "destination_uuid": "90614677-7caa-49c0-a585-b972634acd31",
          "uuid": "b40e85fb-2ad3-4efe-bebf-de3921236c1b"
        }
      ],
      "uuid": "50672de5-38bd-47c0-b63f-699be3126691"
    },
    {
      "actions": [
        {
          "attachments": [],
          "quick_replies": [],
          "text": "Sorry, I don't understand what you mean.",
          "type": "send_msg",
          "uuid": "1553d9eb-940b-45d7-8cde-65b44169355e"
        }
      ],
      "exits": [
        {
          "destination_uuid": "50672de5-38bd-47c0-b63f-699be3126691",
          "uuid": "50cb527d-5e1e-4b37-9834-cedaa1fe8873"
        }
      ],
      "uuid": "84e69394-7cc9-46fe-812e-7be7c6317cad"
    },
    {
      "actions": [
        {
          "attachments": [],
          "quick_replies": [],
          "text": "You have the following completed skills in your Parenting Toolkit:",
          "type": "send_msg",
          "uuid": "7b406e75-a018-44d4-b376-c8d359924b4f"
        },
        {
          "category": "",
          "name": "type_of_toolkit",
          "type": "set_run_result",
          "uuid": "05cd3b06-af3a-448d-93d0-674c4f1a2bfd",
          "value": "full_toolkit"
        }
      ],
      "exits": [
        {
          "destination_uuid": "d9372265-a1b4-4308-a37a-922a4ba88f40",
          "uuid": "70824cd5-bd93-4949-bf54-37fd28307000"
        }
      ],
      "uuid": "bb49efe8-5184-4216-85d3-87b08206c37c"
    },
    {
      "actions": [],
      "exits": [
        {
          "destination_uuid": "26719023-7df9-4c61-b0bd-181634b277f9",
          "uuid": "a019d3ad-f791-4ec7-940b-69b10df33d57"
        },
        {
          "destination_uuid": "6cab33c0-f168-46cf-899b-2fc2fe9333d6",
          "uuid": "f81d25a8-7f16-4702-8f66-93c842e452c8"
        }
      ],
      "router": {
        "cases": [
          {
            "arguments": [
              "["
            ],
            "category_uuid": "d720b95a-6a74-465d-87ca-31c6a3c16fc8",
            "type": "has_only_phrase",
            "uuid": "be541bae-c562-4070-9ce0-fb183c49ddcc"
          }
        ],
        "categories": [
          {
            "exit_uuid": "a019d3ad-f791-4ec7-940b-69b10df33d57",
            "name": "no skills",
            "uuid": "d720b95a-6a74-465d-87ca-31c6a3c16fc8"
          },
          {
            "exit_uuid": "f81d25a8-7f16-4702-8f66-93c842e452c8",
            "name": "Other",
            "uuid": "b76ab6da-71d5-4192-b157-c49fa89b635e"
          }
        ],
        "default_category_uuid": "b76ab6da-71d5-4192-b157-c49fa89b635e",
        "operand": "@fields.incomplete_toolkit",
        "type": "switch"
      },
      "uuid": "703177b3-da7b-4d32-b131-c8715be98d43"
    },
    {
      "actions": [],
      "exits": [
        {
          "destination_uuid": "a711e9af-2dc3-4f3a-ac6e-1a487b49a5ee",
          "uuid": "21297dc0-ba26-499d-afd6-c2df27671ba1"
        },
        {
          "destination_uuid": "703177b3-da7b-4d32-b131-c8715be98d43",
          "uuid": "ca6a41d2-1eae-461d-a86c-266fbc008186"
        },
        {
          "destination_uuid": "bc5c0660-aa61-41d1-9257-26b7f0f66e09",
          "uuid": "c5e66b5c-28c9-45d1-a484-5023a6cf5add"
        },
        {
          "destination_uuid": "84e69394-7cc9-46fe-812e-7be7c6317cad",
          "uuid": "83103230-b91d-4aa6-8ffe-1f6e5bc80ddc"
        }
      ],
      "router": {
        "cases": [
          {
            "arguments": [
              "toolkit"
            ],
            "category_uuid": "b8803c3e-e084-4f01-a306-5388b59125cf",
            "type": "has_any_word",
            "uuid": "f466f47c-4a67-4075-bdcd-9958a28e7b96"
          },
          {
            "arguments": [
              "incomplete"
            ],
            "category_uuid": "05212ae8-7578-45a8-a2d4-34fe4bea3801",
            "type": "has_any_word",
            "uuid": "83f6a49f-1e93-4f98-a612-a8dc5385e9f5"
          },
          {
            "arguments": [
              "back"
            ],
            "category_uuid": "4484168e-aec1-439d-86dd-38c53492b008",
            "type": "has_any_word",
            "uuid": "6c1131f7-1738-4208-a919-4d9eb9c9d9db"
          }
        ],
        "categories": [
          {
            "exit_uuid": "21297dc0-ba26-499d-afd6-c2df27671ba1",
            "name": "toolkit",
            "uuid": "b8803c3e-e084-4f01-a306-5388b59125cf"
          },
          {
            "exit_uuid": "ca6a41d2-1eae-461d-a86c-266fbc008186",
            "name": "incomplete",
            "uuid": "05212ae8-7578-45a8-a2d4-34fe4bea3801"
          },
          {
            "exit_uuid": "c5e66b5c-28c9-45d1-a484-5023a6cf5add",
            "name": "Back",
            "uuid": "4484168e-aec1-439d-86dd-38c53492b008"
          },
          {
            "exit_uuid": "83103230-b91d-4aa6-8ffe-1f6e5bc80ddc",
            "name": "Other",
            "uuid": "e5ee1ee8-3c25-4783-a664-20562274c608"
          }
        ],
        "default_category_uuid": "e5ee1ee8-3c25-4783-a664-20562274c608",
        "operand": "@input.text",
        "result_name": "Result 1",
        "type": "switch",
        "wait": {
          "type": "msg"
        }
      },
      "uuid": "90614677-7caa-49c0-a585-b972634acd31"
    },
    {
      "actions": [
        {
          "attachments": [],
          "quick_replies": [],
          "text": "You have made progress on the following skills:",
          "type": "send_msg",
          "uuid": "724b31f5-2fce-4385-8b2f-cc164fd8beb0"
        },
        {
          "category": "",
          "name": "type_of_toolkit",
          "type": "set_run_result",
          "uuid": "05c327fa-3b5e-479f-8556-22aa23167a7a",
          "value": "full_incomplete"
        }
      ],
      "exits": [
        {
          "destination_uuid": "bdfd477a-a78e-4164-9593-7742aa7d9ee4",
          "uuid": "97d42371-2a1b-48fc-8fae-180dfcdac4e1"
        }
      ],
      "uuid": "6cab33c0-f168-46cf-899b-2fc2fe9333d6"
    },
    {
      "actions": [],
      "exits": [
        {
          "destination_uuid": "db6ded62-b361-4764-92b5-ca57d18b57b6",
          "uuid": "054ff6ed-4457-4b31-bc62-e3701903b365"
        },
        {
          "destination_uuid": "bb49efe8-5184-4216-85d3-87b08206c37c",
          "uuid": "bfe2b972-0a7a-45c9-9e28-fd941cdb07ac"
        }
      ],
      "router": {
        "cases": [
          {
            "arguments": [
              "["
            ],
            "category_uuid": "fb473f2e-1baa-4652-b4aa-4a3fbb772b1e",
            "type": "has_only_phrase",
            "uuid": "bfbb8877-328c-41ba-bedd-1fb5578dec15"
          }
        ],
        "categories": [
          {
            "exit_uuid": "054ff6ed-4457-4b31-bc62-e3701903b365",
            "name": "no skills",
            "uuid": "fb473f2e-1baa-4652-b4aa-4a3fbb772b1e"
          },
          {
            "exit_uuid": "bfe2b972-0a7a-45c9-9e28-fd941cdb07ac",
            "name": "Other",
            "uuid": "b6629f08-2154-4782-8ba8-7b4da544b6a5"
          }
        ],
        "default_category_uuid": "b6629f08-2154-4782-8ba8-7b4da544b6a5",
        "operand": "@fields.toolkit",
        "type": "switch"
      },
      "uuid": "a711e9af-2dc3-4f3a-ac6e-1a487b49a5ee"
    },
    {
      "actions": [
        {
          "flow": {
            "name": "PLH - Internal - Print parenting toolkits",
            "uuid": "43f2c34f-3646-414c-8cf9-cc3edfadea0b"
          },
          "type": "enter_flow",
          "uuid": "2cd3c1ff-c0c4-4ce9-841d-82264fedfdda"
        }
      ],
      "exits": [
        {
          "destination_uuid": "86855813-cacf-4ce2-a909-2a9d76593d55",
          "uuid": "82ada587-012d-43ff-8967-623dc772ac02"
        },
        {
          "destination_uuid": null,
          "uuid": "10f5ba04-2c79-4692-bac8-527f6c70593f"
        }
      ],
      "router": {
        "cases": [
          {
            "arguments": [
              "completed"
            ],
            "category_uuid": "8abb4bcb-866d-477a-bdff-25859368d1df",
            "type": "has_only_text",
            "uuid": "3e7b0083-11cb-44f2-9b7e-b8d0c0eff52c"
          },
          {
            "arguments": [
              "expired"
            ],
            "category_uuid": "6e36acc5-e673-4e90-9259-5a347aa6c455",
            "type": "has_only_text",
            "uuid": "53631cc2-061c-4353-a4b4-05daaa2fa6fb"
          }
        ],
        "categories": [
          {
            "exit_uuid": "82ada587-012d-43ff-8967-623dc772ac02",
            "name": "Complete",
            "uuid": "8abb4bcb-866d-477a-bdff-25859368d1df"
          },
          {
            "exit_uuid": "10f5ba04-2c79-4692-bac8-527f6c70593f",
            "name": "Expired",
            "uuid": "6e36acc5-e673-4e90-9259-5a347aa6c455"
          }
        ],
        "default_category_uuid": "6e36acc5-e673-4e90-9259-5a347aa6c455",
        "operand": "@child.run.status",
        "type": "switch"
      },
      "uuid": "d9372265-a1b4-4308-a37a-922a4ba88f40"
    },
    {
      "actions": [
        {
          "attachments": [],
          "quick_replies": [],
          "text": "You don't have any incomplete skill.",
          "type": "send_msg",
          "uuid": "efd892ee-48ba-4228-ba61-b752d2860af9"
        }
      ],
      "exits": [
        {
          "destination_uuid": "27b563aa-75a5-45a0-930c-43a8796fbcbf",
          "uuid": "6925c0ae-2b40-4f16-8f4e-2abefc3f6c49"
        }
      ],
      "uuid": "26719023-7df9-4c61-b0bd-181634b277f9"
    },
    {
      "actions": [
        {
          "flow": {
            "name": "PLH - Internal - Print parenting toolkits",
            "uuid": "43f2c34f-3646-414c-8cf9-cc3edfadea0b"
          },
          "type": "enter_flow",
          "uuid": "9dfea388-a368-48fb-94d6-81671743153f"
        }
      ],
      "exits": [
        {
          "destination_uuid": "77118c51-ade8-400c-8bc8-ca01e4cc40cd",
          "uuid": "88124be8-7669-4246-ae3d-e317fed3adeb"
        },
        {
          "destination_uuid": null,
          "uuid": "d036b338-c3ec-467d-851e-d950f5882b34"
        }
      ],
      "router": {
        "cases": [
          {
            "arguments": [
              "completed"
            ],
            "category_uuid": "e055d52e-4f9a-4069-a009-8ea32515cdb1",
            "type": "has_only_text",
            "uuid": "1d747019-2e15-4c62-9f72-2c51f9f82a6f"
          },
          {
            "arguments": [
              "expired"
            ],
            "category_uuid": "49c7afd0-f90e-4b51-bba2-7db563c0f489",
            "type": "has_only_text",
            "uuid": "5963d027-5528-4002-a558-c6293690469a"
          }
        ],
        "categories": [
          {
            "exit_uuid": "88124be8-7669-4246-ae3d-e317fed3adeb",
            "name": "Complete",
            "uuid": "e055d52e-4f9a-4069-a009-8ea32515cdb1"
          },
          {
            "exit_uuid": "d036b338-c3ec-467d-851e-d950f5882b34",
            "name": "Expired",
            "uuid": "49c7afd0-f90e-4b51-bba2-7db563c0f489"
          }
        ],
        "default_category_uuid": "49c7afd0-f90e-4b51-bba2-7db563c0f489",
        "operand": "@child.run.status",
        "type": "switch"
      },
      "uuid": "bdfd477a-a78e-4164-9593-7742aa7d9ee4"
    },
    {
      "actions": [
        {
          "attachments": [],
          "quick_replies": [],
          "text": "You don't have any completed skill in your parenting toolkit yet.",
          "type": "send_msg",
          "uuid": "db46fe05-dfec-4c66-ab08-12f3c54d594e"
        }
      ],
      "exits": [
        {
          "destination_uuid": "27b563aa-75a5-45a0-930c-43a8796fbcbf",
          "uuid": "c07af5d3-7a13-4a7b-84b4-2b7c93cd679d"
        }
      ],
      "uuid": "db6ded62-b361-4764-92b5-ca57d18b57b6"
    },
    {
      "actions": [
        {
          "attachments": [],
          "quick_replies": [],
          "text": "Type the number corresponding to the skill to receive messages about this topic again. \n\nType \"back\" if you want to go back to the previous options.",
          "type": "send_msg",
          "uuid": "9194e193-b7bc-4f45-b36a-36cb01723713"
        },
        {
          "category": "",
          "name": "n skills",
          "type": "set_run_result",
          "uuid": "de7cf65e-b672-40c0-b7c7-9c09f2074df4",
          "value": "@(count(split(child.results.list_of_skills,\",\")))"
        }
      ],
      "exits": [
        {
          "destination_uuid": "5f90c4cc-f920-49e7-a459-f274980d6026",
          "uuid": "1d9068f1-2506-459f-abc8-8625db6df9ed"
        }
      ],
      "uuid": "86855813-cacf-4ce2-a909-2a9d76593d55"
    },
    {
      "actions": [
        {
          "flow": {
            "name": "PLH - Help - Entry",
            "uuid": "3aad1291-ad9a-4a18-bb99-d5357e49345b"
          },
          "type": "enter_flow",
          "uuid": "330ea27c-f780-40e1-bec2-d978d6a0e009"
        }
      ],
      "exits": [
        {
          "destination_uuid": null,
          "uuid": "731e8b5a-d43e-4543-98b3-dbd594b15efb"
        },
        {
          "destination_uuid": null,
          "uuid": "39133010-27b3-4f32-9249-6d363e4c7582"
        }
      ],
      "router": {
        "cases": [
          {
            "arguments": [
              "completed"
            ],
            "category_uuid": "4eda9e01-5177-4bb9-b594-3827137d35e0",
            "type": "has_only_text",
            "uuid": "3ab16b99-5bd6-4280-a5df-e63619c3c6db"
          },
          {
            "arguments": [
              "expired"
            ],
            "category_uuid": "0a1a0774-565d-465e-bd63-9b6dbd7ce474",
            "type": "has_only_text",
            "uuid": "54191372-8050-4de6-8409-7bab0bba96c8"
          }
        ],
        "categories": [
          {
            "exit_uuid": "731e8b5a-d43e-4543-98b3-dbd594b15efb",
            "name": "Complete",
            "uuid": "4eda9e01-5177-4bb9-b594-3827137d35e0"
          },
          {
            "exit_uuid": "39133010-27b3-4f32-9249-6d363e4c7582",
            "name": "Expired",
            "uuid": "0a1a0774-565d-465e-bd63-9b6dbd7ce474"
          }
        ],
        "default_category_uuid": "0a1a0774-565d-465e-bd63-9b6dbd7ce474",
        "operand": "@child.run.status",
        "type": "switch"
      },
      "uuid": "bc5c0660-aa61-41d1-9257-26b7f0f66e09"
    },
    {
      "actions": [
        {
          "attachments": [],
          "quick_replies": [],
          "text": "Sorry, I don't understand what you mean. Please reply with a number between 1 and @results.n_skills for receiving messages about that topic again. \n\nType \"back\" if you want to go back to the previous options.",
          "type": "send_msg",
          "uuid": "05fadc25-b0a5-4ead-8c9d-d134101a39e9"
        }
      ],
      "exits": [
        {
          "destination_uuid": "5f90c4cc-f920-49e7-a459-f274980d6026",
          "uuid": "747f8225-f41d-4785-a302-6d5788f6ee32"
        }
      ],
      "uuid": "e1c7d119-c381-4c95-8e34-e4fe550576f4"
    },
    {
      "actions": [],
      "exits": [
        {
          "destination_uuid": "8ae5fd77-15f7-4893-b323-b5d2be6c7353",
          "uuid": "ea82e8e0-a214-4143-b380-cfb9f68f19a6"
        },
        {
          "destination_uuid": "50672de5-38bd-47c0-b63f-699be3126691",
          "uuid": "74e0b5cf-0e37-4566-b52f-7f27cf744138"
        },
        {
          "destination_uuid": "e1c7d119-c381-4c95-8e34-e4fe550576f4",
          "uuid": "03625b4a-9306-41a7-ad0d-3549200cd59c"
        }
      ],
      "router": {
        "cases": [
          {
            "arguments": [
              "1"
            ],
            "category_uuid": "d98dfa3e-93bf-44b8-a68f-402f0e0c9a72",
            "type": "has_number_gte",
            "uuid": "ccca14d3-f7d0-42a9-a47b-be4f4f3455ef"
          },
          {
            "arguments": [
              "back"
            ],
            "category_uuid": "52e45146-c6c1-40fa-a1b4-d0c054335d48",
            "type": "has_any_word",
            "uuid": "1b7b87d1-a39e-48f1-a7a5-77b224a1d8dd"
          }
        ],
        "categories": [
          {
            "exit_uuid": "ea82e8e0-a214-4143-b380-cfb9f68f19a6",
            "name": ">= 1",
            "uuid": "d98dfa3e-93bf-44b8-a68f-402f0e0c9a72"
          },
          {
            "exit_uuid": "74e0b5cf-0e37-4566-b52f-7f27cf744138",
            "name": "Back",
            "uuid": "52e45146-c6c1-40fa-a1b4-d0c054335d48"
          },
          {
            "exit_uuid": "03625b4a-9306-41a7-ad0d-3549200cd59c",
            "name": "Other",
            "uuid": "e6394f83-17e6-4913-8d9b-8813a91dbce5"
          }
        ],
        "default_category_uuid": "e6394f83-17e6-4913-8d9b-8813a91dbce5",
        "operand": "@input.text",
        "result_name": "selected skill",
        "type": "switch",
        "wait": {
          "type": "msg"
        }
      },
      "uuid": "5f90c4cc-f920-49e7-a459-f274980d6026"
    },
    {
      "actions": [],
      "exits": [
        {
          "destination_uuid": "60859110-5194-4a11-b479-e2d7f4ad5f15",
          "uuid": "3b2df7e3-9de5-4129-9a58-bb7b2910bdac"
        },
        {
          "destination_uuid": "bc5c0660-aa61-41d1-9257-26b7f0f66e09",
          "uuid": "92f10e77-7da8-41c4-9d17-06e14062cbdb"
        },
        {
          "destination_uuid": "3004d9fc-38cf-439e-b6c2-8bd59d714186",
          "uuid": "5816b425-9d3d-4d8a-b0df-adda42374c1b"
        }
      ],
      "router": {
        "cases": [
          {
            "arguments": [
              "1"
            ],
            "category_uuid": "8751aea4-b923-48ee-b130-72e495cc5e50",
            "type": "has_number_gte",
            "uuid": "7f30c0eb-48f5-4ee9-8931-33b0990ca2df"
          },
          {
            "arguments": [
              "back"
            ],
            "category_uuid": "cb4fbbeb-d494-4e3a-8829-691290d95b64",
            "type": "has_any_word",
            "uuid": "a04c9c49-134e-423f-ba22-a2e6e6d0901f"
          }
        ],
        "categories": [
          {
            "exit_uuid": "3b2df7e3-9de5-4129-9a58-bb7b2910bdac",
            "name": ">= 1",
            "uuid": "8751aea4-b923-48ee-b130-72e495cc5e50"
          },
          {
            "exit_uuid": "92f10e77-7da8-41c4-9d17-06e14062cbdb",
            "name": "Back",
            "uuid": "cb4fbbeb-d494-4e3a-8829-691290d95b64"
          },
          {
            "exit_uuid": "5816b425-9d3d-4d8a-b0df-adda42374c1b",
            "name": "Other",
            "uuid": "bca815ff-6d74-485e-b76a-3f975419486e"
          }
        ],
        "default_category_uuid": "bca815ff-6d74-485e-b76a-3f975419486e",
        "operand": "@input.text",
        "result_name": "selected skill",
        "type": "switch",
        "wait": {
          "type": "msg"
        }
      },
      "uuid": "d5a0a460-3760-4f6e-ac00-c363cf585b27"
    },
    {
      "actions": [],
      "exits": [
        {
          "destination_uuid": "c77bfe10-c6a9-47d2-bb52-9037b4c41cf5",
          "uuid": "f366f987-81d0-4c4f-bf17-b2721e582780"
        },
        {
          "destination_uuid": "e1c7d119-c381-4c95-8e34-e4fe550576f4",
          "uuid": "5e583598-3665-47c1-83e4-fbd559f9d9e9"
        }
      ],
      "router": {
        "cases": [
          {
            "arguments": [
              "@results.n_skills"
            ],
            "category_uuid": "ee9052a7-70bd-4998-b21f-5f57394ceda7",
            "type": "has_number_lte",
            "uuid": "5ddb90e8-3de0-4199-8491-57dca8898d7d"
          }
        ],
        "categories": [
          {
            "exit_uuid": "f366f987-81d0-4c4f-bf17-b2721e582780",
            "name": "<= Results",
            "uuid": "ee9052a7-70bd-4998-b21f-5f57394ceda7"
          },
          {
            "exit_uuid": "5e583598-3665-47c1-83e4-fbd559f9d9e9",
            "name": "Other",
            "uuid": "65cd002b-b624-43c5-8322-e4e1cef774a5"
          }
        ],
        "default_category_uuid": "65cd002b-b624-43c5-8322-e4e1cef774a5",
        "operand": "@results.selected_skill",
        "type": "switch"
      },
      "uuid": "8ae5fd77-15f7-4893-b323-b5d2be6c7353"
    },
    {
      "actions": [],
      "exits": [
        {
          "destination_uuid": "c77bfe10-c6a9-47d2-bb52-9037b4c41cf5",
          "uuid": "fcc507f7-4091-4d10-bd57-b3cee4162964"
        },
        {
          "destination_uuid": "3004d9fc-38cf-439e-b6c2-8bd59d714186",
          "uuid": "5e73fd4a-5d98-4317-88fd-3914df663082"
        }
      ],
      "router": {
        "cases": [
          {
            "arguments": [
              "@results.n_skills"
            ],
            "category_uuid": "6032d919-d65d-4247-a345-02c4f3a92994",
            "type": "has_number_lte",
            "uuid": "de0bdeee-8b66-42f1-bae5-4565263240d8"
          }
        ],
        "categories": [
          {
            "exit_uuid": "fcc507f7-4091-4d10-bd57-b3cee4162964",
            "name": "<= Results",
            "uuid": "6032d919-d65d-4247-a345-02c4f3a92994"
          },
          {
            "exit_uuid": "5e73fd4a-5d98-4317-88fd-3914df663082",
            "name": "Other",
            "uuid": "3224e1b7-ba3a-40d1-b40f-68287a7b7fe2"
          }
        ],
        "default_category_uuid": "3224e1b7-ba3a-40d1-b40f-68287a7b7fe2",
        "operand": "@results.selected_skill",
        "type": "switch"
      },
      "uuid": "60859110-5194-4a11-b479-e2d7f4ad5f15"
    },
    {
      "actions": [
        {
          "attachments": [],
          "quick_replies": [],
          "text": "Type the number corresponding to the skill to complete it for your Parenting Toolkit. \n\nType \"back\" if you want to go back to the previous options.",
          "type": "send_msg",
          "uuid": "87cc4499-d474-4c36-9f06-4300a96fe7cd"
        },
        {
          "category": "",
          "name": "n skills",
          "type": "set_run_result",
          "uuid": "7ecf691a-8e09-41b0-91e4-8c334aa874b4",
          "value": "@(count(split(child.results.list_of_skills,\",\")))"
        }
      ],
      "exits": [
        {
          "destination_uuid": "d5a0a460-3760-4f6e-ac00-c363cf585b27",
          "uuid": "6cb77193-455e-4612-af13-cd88af82d229"
        }
      ],
      "uuid": "77118c51-ade8-400c-8bc8-ca01e4cc40cd"
    },
    {
      "actions": [
        {
          "category": "",
          "name": "index of skill",
          "type": "set_run_result",
          "uuid": "72de992c-c6dd-46a6-bc69-8da0362ec6ab",
          "value": "@(split(child.results.list_of_skills,\",\")[results.selected_skill -1])"
        }
      ],
      "exits": [
        {
          "destination_uuid": "b687cf52-17cc-47a1-b5a9-22d690ec7072",
          "uuid": "606c6f6b-65db-42a9-8395-30f3eba007b1"
        }
      ],
      "uuid": "c77bfe10-c6a9-47d2-bb52-9037b4c41cf5"
    },
    {
      "actions": [
        {
          "attachments": [],
          "quick_replies": [],
          "text": "Sorry, I don't understand what you mean. Please reply with a number between 1 and @results.n_skills for completing the corresponding skill.\n \nType \"back\" if you want to go back to the previous options.",
          "type": "send_msg",
          "uuid": "99aa3b7b-aea3-4175-9f48-8b59f061994a"
        }
      ],
      "exits": [
        {
          "destination_uuid": "d5a0a460-3760-4f6e-ac00-c363cf585b27",
          "uuid": "72e9d6de-8b26-49d3-a4b2-4d0b10a94fd8"
        }
      ],
      "uuid": "3004d9fc-38cf-439e-b6c2-8bd59d714186"
    },
    {
      "actions": [
        {
          "flow": {
            "name": "Online flow",
            "uuid": "8ee91956-d382-4b11-8d87-e7caacc5d57e"
          },
          "type": "enter_flow",
          "uuid": "703c4e88-9134-46d7-900c-ebaadbc16624"
        }
      ],
      "exits": [
        {
          "destination_uuid": "27b563aa-75a5-45a0-930c-43a8796fbcbf",
          "uuid": "a4848c7d-820d-4670-8ce4-1ca4f3deeb09"
        },
        {
          "destination_uuid": null,
          "uuid": "c871e8d3-2cf1-414f-89aa-3890c4c2298f"
        }
      ],
      "router": {
        "cases": [
          {
            "arguments": [
              "completed"
            ],
            "category_uuid": "e4799afa-2fc0-436d-b771-d8fc31644823",
            "type": "has_only_text",
            "uuid": "071fa201-c3b6-45f2-b40b-961ac58b4a36"
          },
          {
            "arguments": [
              "expired"
            ],
            "category_uuid": "7115f9f4-0b16-4754-8f63-4558e37ad5eb",
            "type": "has_only_text",
            "uuid": "8cb562d1-472b-4cdf-acb3-a0804bc0f396"
          }
        ],
        "categories": [
          {
            "exit_uuid": "a4848c7d-820d-4670-8ce4-1ca4f3deeb09",
            "name": "Complete",
            "uuid": "e4799afa-2fc0-436d-b771-d8fc31644823"
          },
          {
            "exit_uuid": "c871e8d3-2cf1-414f-89aa-3890c4c2298f",
            "name": "Expired",
            "uuid": "7115f9f4-0b16-4754-8f63-4558e37ad5eb"
          }
        ],
        "default_category_uuid": "7115f9f4-0b16-4754-8f63-4558e37ad5eb",
        "operand": "@child.run.status",
        "type": "switch"
      },
      "uuid": "74261f31-b91b-410a-b96f-8ec8ab1469df"
    },
    {
      "actions": [
        {
          "flow": {
            "name": "BehaveFlow - one-on-one time",
            "uuid": "fa62e24a-204a-4092-aa68-7f568cc1cf95"
          },
          "type": "enter_flow",
          "uuid": "65f39046-ec43-408e-a313-47ec18f128e0"
        }
      ],
      "exits": [
        {
          "destination_uuid": "27b563aa-75a5-45a0-930c-43a8796fbcbf",
          "uuid": "7f85026d-2f17-4136-aa72-3e3ca2b37e93"
        },
        {
          "destination_uuid": null,
          "uuid": "c114754a-0d2e-4f94-a884-c745fbd7f936"
        }
      ],
      "router": {
        "cases": [
          {
            "arguments": [
              "completed"
            ],
            "category_uuid": "b55ae8a4-03ac-45b6-b2c1-29173cbb0d69",
            "type": "has_only_text",
            "uuid": "2029853c-ffc3-465e-9bcc-15256df7241e"
          },
          {
            "arguments": [
              "expired"
            ],
            "category_uuid": "3d23761d-6d92-49c3-a2ec-eb7049a20c46",
            "type": "has_only_text",
            "uuid": "267d9753-07d7-433c-8cfc-b483192cc2b9"
          }
        ],
        "categories": [
          {
            "exit_uuid": "7f85026d-2f17-4136-aa72-3e3ca2b37e93",
            "name": "Complete",
            "uuid": "b55ae8a4-03ac-45b6-b2c1-29173cbb0d69"
          },
          {
            "exit_uuid": "c114754a-0d2e-4f94-a884-c745fbd7f936",
            "name": "Expired",
            "uuid": "3d23761d-6d92-49c3-a2ec-eb7049a20c46"
          }
        ],
        "default_category_uuid": "3d23761d-6d92-49c3-a2ec-eb7049a20c46",
        "operand": "@child.run.status",
        "type": "switch"
      },
      "uuid": "c5f33880-b3b7-40b1-9c8d-1f11ed603ea4"
    },
    {
      "actions": [
        {
          "flow": {
            "name": "T3 - positive: Rules",
            "uuid": "60b7961b-13a8-4670-a966-748ec8f06766"
          },
          "type": "enter_flow",
          "uuid": "cbaaaff9-9a9a-4ba6-a497-2208086c90da"
        }
      ],
      "exits": [
        {
          "destination_uuid": "27b563aa-75a5-45a0-930c-43a8796fbcbf",
          "uuid": "b6aa9185-1cc9-4e9d-b066-164e05d7beb1"
        },
        {
          "destination_uuid": null,
          "uuid": "7bf446da-4df4-4531-b10f-dbdfd5e0af60"
        }
      ],
      "router": {
        "cases": [
          {
            "arguments": [
              "completed"
            ],
            "category_uuid": "bbf336dd-f1c1-4aad-a1e2-864991377659",
            "type": "has_only_text",
            "uuid": "464f1695-bec8-42bf-8e7e-a96de4274274"
          },
          {
            "arguments": [
              "expired"
            ],
            "category_uuid": "48be3dd4-6bca-4ef3-a3b5-4733b34da29f",
            "type": "has_only_text",
            "uuid": "ff8619ce-2f34-4ce9-a214-4edb4beb185b"
          }
        ],
        "categories": [
          {
            "exit_uuid": "b6aa9185-1cc9-4e9d-b066-164e05d7beb1",
            "name": "Complete",
            "uuid": "bbf336dd-f1c1-4aad-a1e2-864991377659"
          },
          {
            "exit_uuid": "7bf446da-4df4-4531-b10f-dbdfd5e0af60",
            "name": "Expired",
            "uuid": "48be3dd4-6bca-4ef3-a3b5-4733b34da29f"
          }
        ],
        "default_category_uuid": "48be3dd4-6bca-4ef3-a3b5-4733b34da29f",
        "operand": "@child.run.status",
        "type": "switch"
      },
      "uuid": "96f73aef-7c35-4302-ab0e-15ae2d1c0ddf"
    },
    {
      "actions": [
        {
          "flow": {
            "name": "BehaveFlow - Crying",
            "uuid": "42a695f9-813a-4cb3-927a-d642b1ddb916"
          },
          "type": "enter_flow",
          "uuid": "4c56304b-5017-4239-87d0-e18e2fbdeb7d"
        }
      ],
      "exits": [
        {
          "destination_uuid": "27b563aa-75a5-45a0-930c-43a8796fbcbf",
          "uuid": "da111d37-24b1-47b7-8900-1341247d08f3"
        },
        {
          "destination_uuid": null,
          "uuid": "a367378f-cc6a-4bd9-b3d4-a4fabc7ce2b7"
        }
      ],
      "router": {
        "cases": [
          {
            "arguments": [
              "completed"
            ],
            "category_uuid": "800a0b10-8464-472a-b99a-25e64636b8cb",
            "type": "has_only_text",
            "uuid": "eb5d2ad9-34b5-4376-a98d-030e2f60dff4"
          },
          {
            "arguments": [
              "expired"
            ],
            "category_uuid": "ddfb643e-41c6-4e23-9ffa-4c733b905fbd",
            "type": "has_only_text",
            "uuid": "4613b290-14eb-4fa7-bd8e-5d463d770cc9"
          }
        ],
        "categories": [
          {
            "exit_uuid": "da111d37-24b1-47b7-8900-1341247d08f3",
            "name": "Complete",
            "uuid": "800a0b10-8464-472a-b99a-25e64636b8cb"
          },
          {
            "exit_uuid": "a367378f-cc6a-4bd9-b3d4-a4fabc7ce2b7",
            "name": "Expired",
            "uuid": "ddfb643e-41c6-4e23-9ffa-4c733b905fbd"
          }
        ],
        "default_category_uuid": "ddfb643e-41c6-4e23-9ffa-4c733b905fbd",
        "operand": "@child.run.status",
        "type": "switch"
      },
      "uuid": "38b6223a-fd99-4b96-bedd-cf6ec6dcf44b"
    },
    {
      "actions": [
        {
          "flow": {
            "name": "Adult5-calm: Take a pause",
            "uuid": "cb2e0d0a-0c54-4d40-8fba-09b1456779fa"
          },
          "type": "enter_flow",
          "uuid": "3f58ee7a-4724-4d72-b84d-b43eb35c3c6c"
        }
      ],
      "exits": [
        {
          "destination_uuid": "27b563aa-75a5-45a0-930c-43a8796fbcbf",
          "uuid": "e0de3fb6-5698-459c-9628-28d06e0296e5"
        },
        {
          "destination_uuid": null,
          "uuid": "dabb3362-7d26-44df-8ea3-d73394f6b317"
        }
      ],
      "router": {
        "cases": [
          {
            "arguments": [
              "completed"
            ],
            "category_uuid": "e88868ed-da4f-44fe-8cf8-692a0cd2c7b3",
            "type": "has_only_text",
            "uuid": "21a0aa8f-ab44-4611-ba41-9eff254a4dbe"
          },
          {
            "arguments": [
              "expired"
            ],
            "category_uuid": "ff94c9cb-ede9-4ea1-8ff9-6ac0a7792db3",
            "type": "has_only_text",
            "uuid": "f4521745-7415-42e7-9db7-1bf25340dac3"
          }
        ],
        "categories": [
          {
            "exit_uuid": "e0de3fb6-5698-459c-9628-28d06e0296e5",
            "name": "Complete",
            "uuid": "e88868ed-da4f-44fe-8cf8-692a0cd2c7b3"
          },
          {
            "exit_uuid": "dabb3362-7d26-44df-8ea3-d73394f6b317",
            "name": "Expired",
            "uuid": "ff94c9cb-ede9-4ea1-8ff9-6ac0a7792db3"
          }
        ],
        "default_category_uuid": "ff94c9cb-ede9-4ea1-8ff9-6ac0a7792db3",
        "operand": "@child.run.status",
        "type": "switch"
      },
      "uuid": "e99c7604-5d60-4295-9d53-6c3eabc3cb90"
    },
    {
      "actions": [
        {
          "flow": {
            "name": "EducationFlow",
            "uuid": "d281a3b5-b601-492a-9a2c-da0a67303ec3"
          },
          "type": "enter_flow",
          "uuid": "4852ba82-8057-4c17-a30c-73fe40c0cc16"
        }
      ],
      "exits": [
        {
          "destination_uuid": "27b563aa-75a5-45a0-930c-43a8796fbcbf",
          "uuid": "cfb72c70-81d9-4474-8b61-d0db6a7a960d"
        },
        {
          "destination_uuid": null,
          "uuid": "3b30af9d-77cf-4a40-85d4-7758c8221c0f"
        }
      ],
      "router": {
        "cases": [
          {
            "arguments": [
              "completed"
            ],
            "category_uuid": "7897b8bc-087a-4ce0-b292-9ee082fb0b90",
            "type": "has_only_text",
            "uuid": "088a5e6a-4fb9-43a5-9e76-6cb055603d19"
          },
          {
            "arguments": [
              "expired"
            ],
            "category_uuid": "5b63e5d1-4a63-4b87-b3a9-2df8d5a4b816",
            "type": "has_only_text",
            "uuid": "3ebbc0c2-f45f-4099-be6b-04bdb140bbf5"
          }
        ],
        "categories": [
          {
            "exit_uuid": "cfb72c70-81d9-4474-8b61-d0db6a7a960d",
            "name": "Complete",
            "uuid": "7897b8bc-087a-4ce0-b292-9ee082fb0b90"
          },
          {
            "exit_uuid": "3b30af9d-77cf-4a40-85d4-7758c8221c0f",
            "name": "Expired",
            "uuid": "5b63e5d1-4a63-4b87-b3a9-2df8d5a4b816"
          }
        ],
        "default_category_uuid": "5b63e5d1-4a63-4b87-b3a9-2df8d5a4b816",
        "operand": "@child.run.status",
        "type": "switch"
      },
      "uuid": "b9abbfbf-6fc2-4a4b-9d7c-5cafec3aae06"
    },
    {
      "actions": [
        {
          "flow": {
            "name": "T2 - Relax: Anger management",
            "uuid": "39f83807-d432-4b59-80d8-6061c761f59c"
          },
          "type": "enter_flow",
          "uuid": "24d38fcd-3601-475b-b5f2-a5d799404ed4"
        }
      ],
      "exits": [
        {
          "destination_uuid": "27b563aa-75a5-45a0-930c-43a8796fbcbf",
          "uuid": "bbcb8479-63c7-40e8-98ef-e490c875c317"
        },
        {
          "destination_uuid": null,
          "uuid": "6097a8b6-ff1c-4c7b-adde-6f00316975b8"
        }
      ],
      "router": {
        "cases": [
          {
            "arguments": [
              "completed"
            ],
            "category_uuid": "daa89415-d20b-4dcc-9773-89a3571fb654",
            "type": "has_only_text",
            "uuid": "966c921c-9f70-4310-ab2d-63e409fdd806"
          },
          {
            "arguments": [
              "expired"
            ],
            "category_uuid": "201a801f-679e-4913-9850-2c2917504d10",
            "type": "has_only_text",
            "uuid": "b7eb0ee3-a08e-4e00-a1fc-41093c581f85"
          }
        ],
        "categories": [
          {
            "exit_uuid": "bbcb8479-63c7-40e8-98ef-e490c875c317",
            "name": "Complete",
            "uuid": "daa89415-d20b-4dcc-9773-89a3571fb654"
          },
          {
            "exit_uuid": "6097a8b6-ff1c-4c7b-adde-6f00316975b8",
            "name": "Expired",
            "uuid": "201a801f-679e-4913-9850-2c2917504d10"
          }
        ],
        "default_category_uuid": "201a801f-679e-4913-9850-2c2917504d10",
        "operand": "@child.run.status",
        "type": "switch"
      },
      "uuid": "e56b17f8-5ed4-4f1c-9852-990fefd704db"
    },
    {
      "actions": [
        {
          "flow": {
            "name": "BehaveFlow - consequences",
            "uuid": "e5fb19b6-addd-45cc-bad2-dd0861472e13"
          },
          "type": "enter_flow",
          "uuid": "e8674096-3c16-4e20-b0f6-eaefa3a7a0fc"
        }
      ],
      "exits": [
        {
          "destination_uuid": "27b563aa-75a5-45a0-930c-43a8796fbcbf",
          "uuid": "c8eead96-464e-4187-9000-216fef21efc7"
        },
        {
          "destination_uuid": null,
          "uuid": "938d186f-05cb-41d9-8872-456f65861948"
        }
      ],
      "router": {
        "cases": [
          {
            "arguments": [
              "completed"
            ],
            "category_uuid": "299bb06e-4050-421d-b0a7-100aaed83543",
            "type": "has_only_text",
            "uuid": "7b025260-3f04-41f3-a4d5-5779c358d9a9"
          },
          {
            "arguments": [
              "expired"
            ],
            "category_uuid": "27bf9863-4a3c-46f1-aef8-859db5bd5253",
            "type": "has_only_text",
            "uuid": "da35878a-5b29-460c-814b-2823371aca60"
          }
        ],
        "categories": [
          {
            "exit_uuid": "c8eead96-464e-4187-9000-216fef21efc7",
            "name": "Complete",
            "uuid": "299bb06e-4050-421d-b0a7-100aaed83543"
          },
          {
            "exit_uuid": "938d186f-05cb-41d9-8872-456f65861948",
            "name": "Expired",
            "uuid": "27bf9863-4a3c-46f1-aef8-859db5bd5253"
          }
        ],
        "default_category_uuid": "27bf9863-4a3c-46f1-aef8-859db5bd5253",
        "operand": "@child.run.status",
        "type": "switch"
      },
      "uuid": "edab3dd3-0bf5-464b-b4ec-fcd14f98cc1d"
    },
    {
      "actions": [
        {
          "flow": {
            "name": "BehaveFlow - be open to emotions",
            "uuid": "530536dd-3ac9-475c-b80b-b0b0659535cd"
          },
          "type": "enter_flow",
          "uuid": "4c2c583c-6fd8-4c17-8228-b74f334a345b"
        }
      ],
      "exits": [
        {
          "destination_uuid": "27b563aa-75a5-45a0-930c-43a8796fbcbf",
          "uuid": "344982d8-11fe-4696-b49a-e23703ec366e"
        },
        {
          "destination_uuid": null,
          "uuid": "933ec990-0314-462c-b716-5c823c59e2d4"
        }
      ],
      "router": {
        "cases": [
          {
            "arguments": [
              "completed"
            ],
            "category_uuid": "91bb33e7-d097-4339-a719-57ed1c2a623b",
            "type": "has_only_text",
            "uuid": "af568614-b9ad-4e15-8526-d8fcbeb0f3bb"
          },
          {
            "arguments": [
              "expired"
            ],
            "category_uuid": "5b4c2076-a5d7-4375-9883-ef48e4815bb2",
            "type": "has_only_text",
            "uuid": "fbe4b4c9-000e-4d78-9994-670bd03b1f60"
          }
        ],
        "categories": [
          {
            "exit_uuid": "344982d8-11fe-4696-b49a-e23703ec366e",
            "name": "Complete",
            "uuid": "91bb33e7-d097-4339-a719-57ed1c2a623b"
          },
          {
            "exit_uuid": "933ec990-0314-462c-b716-5c823c59e2d4",
            "name": "Expired",
            "uuid": "5b4c2076-a5d7-4375-9883-ef48e4815bb2"
          }
        ],
        "default_category_uuid": "5b4c2076-a5d7-4375-9883-ef48e4815bb2",
        "operand": "@child.run.status",
        "type": "switch"
      },
      "uuid": "150d3ac7-46f5-4325-90cc-dbafbc94caf8"
    },
    {
      "actions": [
        {
          "flow": {
            "name": "T3 - Positive: instructions on keeping it positive",
            "uuid": "b1e03180-c408-4311-8ebe-fbbaf623d635"
          },
          "type": "enter_flow",
          "uuid": "092e9a9a-6017-4545-a4ed-b3c341d9a479"
        }
      ],
      "exits": [
        {
          "destination_uuid": "27b563aa-75a5-45a0-930c-43a8796fbcbf",
          "uuid": "4ee5e78f-ba39-4fca-91bc-e1d56323fc75"
        },
        {
          "destination_uuid": null,
          "uuid": "42227ca4-c1f7-4a48-b926-aba287b215ee"
        }
      ],
      "router": {
        "cases": [
          {
            "arguments": [
              "completed"
            ],
            "category_uuid": "5f36bda5-e17c-4318-9ffb-90e35184ade6",
            "type": "has_only_text",
            "uuid": "ef0e1a3b-7fb1-4bdc-945c-0a4eee16bb26"
          },
          {
            "arguments": [
              "expired"
            ],
            "category_uuid": "82ae30a0-4773-48b4-b293-b1a7407d27a8",
            "type": "has_only_text",
            "uuid": "a9949945-1c52-4e60-8d16-756916733527"
          }
        ],
        "categories": [
          {
            "exit_uuid": "4ee5e78f-ba39-4fca-91bc-e1d56323fc75",
            "name": "Complete",
            "uuid": "5f36bda5-e17c-4318-9ffb-90e35184ade6"
          },
          {
            "exit_uuid": "42227ca4-c1f7-4a48-b926-aba287b215ee",
            "name": "Expired",
            "uuid": "82ae30a0-4773-48b4-b293-b1a7407d27a8"
          }
        ],
        "default_category_uuid": "82ae30a0-4773-48b4-b293-b1a7407d27a8",
        "operand": "@child.run.status",
        "type": "switch"
      },
      "uuid": "fd5f6732-40f8-44c5-9e70-b1e5593fc3c9"
    },
    {
      "actions": [
        {
          "flow": {
            "name": "BehaveFlow - redirect",
            "uuid": "f896a544-cb05-43a6-9657-9993a0568e71"
          },
          "type": "enter_flow",
          "uuid": "53bb94d3-a678-4f84-90b8-78fc78331b34"
        }
      ],
      "exits": [
        {
          "destination_uuid": "27b563aa-75a5-45a0-930c-43a8796fbcbf",
          "uuid": "fe2c3989-b243-4d54-b3d2-eb8c85c186a5"
        },
        {
          "destination_uuid": null,
          "uuid": "44304979-845d-4bca-8141-0a441edf6c92"
        }
      ],
      "router": {
        "cases": [
          {
            "arguments": [
              "completed"
            ],
            "category_uuid": "49f2748b-01b1-4baf-8cdc-352838d59062",
            "type": "has_only_text",
            "uuid": "c9e84dc0-2546-4f35-9a94-0c3b79b5d0e3"
          },
          {
            "arguments": [
              "expired"
            ],
            "category_uuid": "b53e58b6-9c80-48e1-b14d-148f82107093",
            "type": "has_only_text",
            "uuid": "5ddb0dc7-d8f3-4221-bc08-07ccf58208d5"
          }
        ],
        "categories": [
          {
            "exit_uuid": "fe2c3989-b243-4d54-b3d2-eb8c85c186a5",
            "name": "Complete",
            "uuid": "49f2748b-01b1-4baf-8cdc-352838d59062"
          },
          {
            "exit_uuid": "44304979-845d-4bca-8141-0a441edf6c92",
            "name": "Expired",
            "uuid": "b53e58b6-9c80-48e1-b14d-148f82107093"
          }
        ],
        "default_category_uuid": "b53e58b6-9c80-48e1-b14d-148f82107093",
        "operand": "@child.run.status",
        "type": "switch"
      },
      "uuid": "f5ec8299-a71b-46d8-a1af-329e1b019d03"
    },
    {
      "actions": [
        {
          "flow": {
            "name": "BehaveFlow - Crisis",
            "uuid": "8b191a0a-6f36-4b8b-8211-d0883ce2d564"
          },
          "type": "enter_flow",
          "uuid": "eca30876-bce8-4c40-9705-16b81bba1c7b"
        }
      ],
      "exits": [
        {
          "destination_uuid": "27b563aa-75a5-45a0-930c-43a8796fbcbf",
          "uuid": "82c4c103-de47-4539-afd7-1a7e85cd9a2b"
        },
        {
          "destination_uuid": null,
          "uuid": "4f73fb57-d2fd-4b5d-b71a-23309fb35bb4"
        }
      ],
      "router": {
        "cases": [
          {
            "arguments": [
              "completed"
            ],
            "category_uuid": "f644e7b7-8689-464d-890b-9ccf29a427e8",
            "type": "has_only_text",
            "uuid": "994ce542-06f6-4a05-abc1-91e1ee641c07"
          },
          {
            "arguments": [
              "expired"
            ],
            "category_uuid": "16b7630c-56e3-4525-9097-afeb229cb694",
            "type": "has_only_text",
            "uuid": "e6c014af-fcfa-4345-ac9c-cdc8f8609b9d"
          }
        ],
        "categories": [
          {
            "exit_uuid": "82c4c103-de47-4539-afd7-1a7e85cd9a2b",
            "name": "Complete",
            "uuid": "f644e7b7-8689-464d-890b-9ccf29a427e8"
          },
          {
            "exit_uuid": "4f73fb57-d2fd-4b5d-b71a-23309fb35bb4",
            "name": "Expired",
            "uuid": "16b7630c-56e3-4525-9097-afeb229cb694"
          }
        ],
        "default_category_uuid": "16b7630c-56e3-4525-9097-afeb229cb694",
        "operand": "@child.run.status",
        "type": "switch"
      },
      "uuid": "40ce064e-705d-4b2e-84bb-bae338c45509"
    },
    {
      "actions": [
        {
          "flow": {
            "name": "BehaveFlow - praise",
            "uuid": "3894dff4-93f0-42a8-92a3-6220bff18bc8"
          },
          "type": "enter_flow",
          "uuid": "d97600e6-69dc-4fe0-b040-1cb08bfb89f1"
        }
      ],
      "exits": [
        {
          "destination_uuid": "27b563aa-75a5-45a0-930c-43a8796fbcbf",
          "uuid": "7b70a8a0-43f0-4af1-85c6-f956c149dc78"
        },
        {
          "destination_uuid": null,
          "uuid": "05372fba-4829-4332-8df2-b06fb9aa218f"
        }
      ],
      "router": {
        "cases": [
          {
            "arguments": [
              "completed"
            ],
            "category_uuid": "6307e685-b907-4ee2-abd1-3a0591ef714d",
            "type": "has_only_text",
            "uuid": "8b01db26-ef0d-451a-b794-03fc5e18425e"
          },
          {
            "arguments": [
              "expired"
            ],
            "category_uuid": "62de635b-52c2-4a51-852b-55ff5eb8a4bd",
            "type": "has_only_text",
            "uuid": "18cef221-9a7c-439e-babe-703c5fc94e04"
          }
        ],
        "categories": [
          {
            "exit_uuid": "7b70a8a0-43f0-4af1-85c6-f956c149dc78",
            "name": "Complete",
            "uuid": "6307e685-b907-4ee2-abd1-3a0591ef714d"
          },
          {
            "exit_uuid": "05372fba-4829-4332-8df2-b06fb9aa218f",
            "name": "Expired",
            "uuid": "62de635b-52c2-4a51-852b-55ff5eb8a4bd"
          }
        ],
        "default_category_uuid": "62de635b-52c2-4a51-852b-55ff5eb8a4bd",
        "operand": "@child.run.status",
        "type": "switch"
      },
      "uuid": "828e7627-5cdb-4477-9429-ffae26840966"
    },
    {
      "actions": [
        {
          "flow": {
            "name": "T2 - Relax CheckIn 17 (Mindful movement)",
            "uuid": "d1e88e1c-34f1-4b60-af2c-a99adc885d7c"
          },
          "type": "enter_flow",
          "uuid": "2a51ab41-2788-41e1-ab49-cbe18fe0fb15"
        }
      ],
      "exits": [
        {
          "destination_uuid": "27b563aa-75a5-45a0-930c-43a8796fbcbf",
          "uuid": "9c213024-afba-48c2-b97e-ab94334ea657"
        },
        {
          "destination_uuid": null,
          "uuid": "ba651947-f2b7-4938-a690-6dc5a6431bd7"
        }
      ],
      "router": {
        "cases": [
          {
            "arguments": [
              "completed"
            ],
            "category_uuid": "6aa4aef4-05cb-43da-8406-08cd0d75f20b",
            "type": "has_only_text",
            "uuid": "9dea3c14-a77a-4fc7-8ae1-f4119a7ba97a"
          },
          {
            "arguments": [
              "expired"
            ],
            "category_uuid": "77649d72-b07a-4f95-abea-60ba618553b5",
            "type": "has_only_text",
            "uuid": "1f0fcc5a-67d6-4b20-972e-076b0e0ea355"
          }
        ],
        "categories": [
          {
            "exit_uuid": "9c213024-afba-48c2-b97e-ab94334ea657",
            "name": "Complete",
            "uuid": "6aa4aef4-05cb-43da-8406-08cd0d75f20b"
          },
          {
            "exit_uuid": "ba651947-f2b7-4938-a690-6dc5a6431bd7",
            "name": "Expired",
            "uuid": "77649d72-b07a-4f95-abea-60ba618553b5"
          }
        ],
        "default_category_uuid": "77649d72-b07a-4f95-abea-60ba618553b5",
        "operand": "@child.run.status",
        "type": "switch"
      },
      "uuid": "b04258f3-405f-4d25-9627-7873147a5f8d"
    },
    {
      "actions": [
        {
          "flow": {
            "name": "T3 - positive: safe/unsafe touch",
            "uuid": "8c08b215-0afe-44fc-9b39-46adc04d087f"
          },
          "type": "enter_flow",
          "uuid": "910e5064-c5db-47f7-a888-20cf463e4dcc"
        }
      ],
      "exits": [
        {
          "destination_uuid": "27b563aa-75a5-45a0-930c-43a8796fbcbf",
          "uuid": "ccf7cd05-da79-4965-bb98-f842aa767395"
        },
        {
          "destination_uuid": null,
          "uuid": "8bd9361c-5acd-4087-935c-d21070d22417"
        }
      ],
      "router": {
        "cases": [
          {
            "arguments": [
              "completed"
            ],
            "category_uuid": "cc6a77f8-28f9-405b-bc87-31669d921bec",
            "type": "has_only_text",
            "uuid": "69b86015-d467-461a-b709-4ee5b0136809"
          },
          {
            "arguments": [
              "expired"
            ],
            "category_uuid": "03561381-5384-419f-a62a-a2086aec2a2b",
            "type": "has_only_text",
            "uuid": "6ba54ee9-1576-4425-9d44-40667fd333da"
          }
        ],
        "categories": [
          {
            "exit_uuid": "ccf7cd05-da79-4965-bb98-f842aa767395",
            "name": "Complete",
            "uuid": "cc6a77f8-28f9-405b-bc87-31669d921bec"
          },
          {
            "exit_uuid": "8bd9361c-5acd-4087-935c-d21070d22417",
            "name": "Expired",
            "uuid": "03561381-5384-419f-a62a-a2086aec2a2b"
          }
        ],
        "default_category_uuid": "03561381-5384-419f-a62a-a2086aec2a2b",
        "operand": "@child.run.status",
        "type": "switch"
      },
      "uuid": "e1382546-aed0-4329-af6c-ccdcd43aba27"
    },
    {
      "actions": [
        {
          "flow": {
            "name": "Baby12-calm: book-sharing",
            "uuid": "431dcaef-2ff5-42e6-b61f-3fc37791f57f"
          },
          "type": "enter_flow",
          "uuid": "a5136c3c-ad6f-413a-b80a-57c58caa4efe"
        }
      ],
      "exits": [
        {
          "destination_uuid": "27b563aa-75a5-45a0-930c-43a8796fbcbf",
          "uuid": "b601a5a2-c0e1-4043-b73f-e81785ca9921"
        },
        {
          "destination_uuid": null,
          "uuid": "52a06998-9699-4f05-9887-f6d91cbc099d"
        }
      ],
      "router": {
        "cases": [
          {
            "arguments": [
              "completed"
            ],
            "category_uuid": "7aeb9f23-44bf-4d35-9120-c8ac096cbf01",
            "type": "has_only_text",
            "uuid": "71586182-863c-474c-b19a-74445eddb5bc"
          },
          {
            "arguments": [
              "expired"
            ],
            "category_uuid": "329f2f92-c877-4d33-b0ef-a49d1f8cc47b",
            "type": "has_only_text",
            "uuid": "d1d9912f-8716-4697-8e5d-a6843acd48a4"
          }
        ],
        "categories": [
          {
            "exit_uuid": "b601a5a2-c0e1-4043-b73f-e81785ca9921",
            "name": "Complete",
            "uuid": "7aeb9f23-44bf-4d35-9120-c8ac096cbf01"
          },
          {
            "exit_uuid": "52a06998-9699-4f05-9887-f6d91cbc099d",
            "name": "Expired",
            "uuid": "329f2f92-c877-4d33-b0ef-a49d1f8cc47b"
          }
        ],
        "default_category_uuid": "329f2f92-c877-4d33-b0ef-a49d1f8cc47b",
        "operand": "@child.run.status",
        "type": "switch"
      },
      "uuid": "f2242e16-ef6e-441e-b7e8-8adfbcf7d741"
    },
    {
      "actions": [
        {
          "flow": {
            "name": "BehaveFlow - routines",
            "uuid": "3a875a61-978c-4873-a2c1-e085f036266a"
          },
          "type": "enter_flow",
          "uuid": "607023b9-c9a5-4076-82dd-86a2e94cf7ed"
        }
      ],
      "exits": [
        {
          "destination_uuid": "27b563aa-75a5-45a0-930c-43a8796fbcbf",
          "uuid": "e957d460-15d3-4958-a555-ff6784e5484e"
        },
        {
          "destination_uuid": null,
          "uuid": "fe9dbb21-168d-47ce-8375-25a914039b85"
        }
      ],
      "router": {
        "cases": [
          {
            "arguments": [
              "completed"
            ],
            "category_uuid": "3396cffa-bbf2-463b-9834-11d15c2c32e4",
            "type": "has_only_text",
            "uuid": "94bce87c-9c55-4fc7-b846-65f17089ebd1"
          },
          {
            "arguments": [
              "expired"
            ],
            "category_uuid": "dccb027b-91c9-40ba-bdec-c949d5cb31cd",
            "type": "has_only_text",
            "uuid": "dd3b0a87-4133-45e2-90e9-02d4b960b5c5"
          }
        ],
        "categories": [
          {
            "exit_uuid": "e957d460-15d3-4958-a555-ff6784e5484e",
            "name": "Complete",
            "uuid": "3396cffa-bbf2-463b-9834-11d15c2c32e4"
          },
          {
            "exit_uuid": "fe9dbb21-168d-47ce-8375-25a914039b85",
            "name": "Expired",
            "uuid": "dccb027b-91c9-40ba-bdec-c949d5cb31cd"
          }
        ],
        "default_category_uuid": "dccb027b-91c9-40ba-bdec-c949d5cb31cd",
        "operand": "@child.run.status",
        "type": "switch"
      },
      "uuid": "2705691c-e6bd-43ae-980f-2b4109b040cd"
    },
    {
      "actions": [
        {
          "flow": {
            "name": "BehaveFlow - ignore",
            "uuid": "bf2d6233-394a-4416-b3a4-0beb60fc56b5"
          },
          "type": "enter_flow",
          "uuid": "03358701-e644-4f4a-a9dc-f1e9fa5f2544"
        }
      ],
      "exits": [
        {
          "destination_uuid": "27b563aa-75a5-45a0-930c-43a8796fbcbf",
          "uuid": "952a2ad0-bd73-4b6d-a18e-ae7654b9fead"
        },
        {
          "destination_uuid": null,
          "uuid": "11f2bf0d-eac2-4537-b69a-813ec7e0eedb"
        }
      ],
      "router": {
        "cases": [
          {
            "arguments": [
              "completed"
            ],
            "category_uuid": "d553041d-0ada-4158-a88f-31e3cd3cc983",
            "type": "has_only_text",
            "uuid": "91b065e5-d6fc-4117-92e0-96de8afd0dd1"
          },
          {
            "arguments": [
              "expired"
            ],
            "category_uuid": "f46760b1-82de-45a3-9a41-ff17960f4ee6",
            "type": "has_only_text",
            "uuid": "593e8420-123a-4eb7-9171-6b6aa6d009c2"
          }
        ],
        "categories": [
          {
            "exit_uuid": "952a2ad0-bd73-4b6d-a18e-ae7654b9fead",
            "name": "Complete",
            "uuid": "d553041d-0ada-4158-a88f-31e3cd3cc983"
          },
          {
            "exit_uuid": "11f2bf0d-eac2-4537-b69a-813ec7e0eedb",
            "name": "Expired",
            "uuid": "f46760b1-82de-45a3-9a41-ff17960f4ee6"
          }
        ],
        "default_category_uuid": "f46760b1-82de-45a3-9a41-ff17960f4ee6",
        "operand": "@child.run.status",
        "type": "switch"
      },
      "uuid": "6a542ecf-83a0-4db1-b744-3f4e53512cf0"
    },
    {
      "actions": [
        {
          "flow": {
            "name": "FamilyFlow",
            "uuid": "dc87cd8d-5d4b-44f6-91d9-5cfa7b1ed631"
          },
          "type": "enter_flow",
          "uuid": "8074f1f2-f3cd-48f0-a4e0-baeac44e17a4"
        }
      ],
      "exits": [
        {
          "destination_uuid": "27b563aa-75a5-45a0-930c-43a8796fbcbf",
          "uuid": "d6477c26-23a1-40b6-8469-952b27f9f6c9"
        },
        {
          "destination_uuid": null,
          "uuid": "16b7793f-0304-4fa5-b60d-9b5c02501f29"
        }
      ],
      "router": {
        "cases": [
          {
            "arguments": [
              "completed"
            ],
            "category_uuid": "7b4deb5f-c8d6-4194-a466-82a6355731c9",
            "type": "has_only_text",
            "uuid": "0099fb2a-8fc1-4fde-98e2-7d1caea39d73"
          },
          {
            "arguments": [
              "expired"
            ],
            "category_uuid": "3f4570f7-bf4d-42cb-b1c6-9fd9e18306a4",
            "type": "has_only_text",
            "uuid": "2c5402e9-6d7e-42b1-8a50-bbf682e0aee0"
          }
        ],
        "categories": [
          {
            "exit_uuid": "d6477c26-23a1-40b6-8469-952b27f9f6c9",
            "name": "Complete",
            "uuid": "7b4deb5f-c8d6-4194-a466-82a6355731c9"
          },
          {
            "exit_uuid": "16b7793f-0304-4fa5-b60d-9b5c02501f29",
            "name": "Expired",
            "uuid": "3f4570f7-bf4d-42cb-b1c6-9fd9e18306a4"
          }
        ],
        "default_category_uuid": "3f4570f7-bf4d-42cb-b1c6-9fd9e18306a4",
        "operand": "@child.run.status",
        "type": "switch"
      },
      "uuid": "ea9cfa3c-84b3-4282-be6e-7b0a15f24aa2"
    },
    {
      "actions": [
        {
          "flow": {
            "name": "DevelopmentFlow",
            "uuid": "cc9b8048-d44d-4bd5-aeb9-d2b32ec5fb1f"
          },
          "type": "enter_flow",
          "uuid": "ab2140e2-8365-4ed0-954a-7c372e0864a6"
        }
      ],
      "exits": [
        {
          "destination_uuid": "27b563aa-75a5-45a0-930c-43a8796fbcbf",
          "uuid": "5b111e0b-3bce-461e-9b25-d0be0fb7a760"
        },
        {
          "destination_uuid": null,
          "uuid": "1217bf98-4650-4014-b6c7-f3ccbd80b7b2"
        }
      ],
      "router": {
        "cases": [
          {
            "arguments": [
              "completed"
            ],
            "category_uuid": "30ea4957-b475-4c63-8fad-419004df4328",
            "type": "has_only_text",
            "uuid": "88e50658-242e-48ba-928f-29edf7a256e3"
          },
          {
            "arguments": [
              "expired"
            ],
            "category_uuid": "2f798542-e144-4852-9024-7333f4176059",
            "type": "has_only_text",
            "uuid": "812d3a5b-94a5-4f59-8af9-8e3fa1cf802d"
          }
        ],
        "categories": [
          {
            "exit_uuid": "5b111e0b-3bce-461e-9b25-d0be0fb7a760",
            "name": "Complete",
            "uuid": "30ea4957-b475-4c63-8fad-419004df4328"
          },
          {
            "exit_uuid": "1217bf98-4650-4014-b6c7-f3ccbd80b7b2",
            "name": "Expired",
            "uuid": "2f798542-e144-4852-9024-7333f4176059"
          }
        ],
        "default_category_uuid": "2f798542-e144-4852-9024-7333f4176059",
        "operand": "@child.run.status",
        "type": "switch"
      },
      "uuid": "f40feb2f-2b4d-4a82-934a-6ec845662dff"
    },
    {
      "actions": [
        {
          "flow": {
            "name": "DisabilityFlow",
            "uuid": "1750e0a7-af13-48a4-8c02-67d8eb2c4e83"
          },
          "type": "enter_flow",
          "uuid": "e4b6a93a-e102-435b-a216-ab80c0f89e90"
        }
      ],
      "exits": [
        {
          "destination_uuid": "27b563aa-75a5-45a0-930c-43a8796fbcbf",
          "uuid": "3b12c3c3-063f-40c7-88b8-f36ba10f7345"
        },
        {
          "destination_uuid": null,
          "uuid": "bd9ab4e3-e189-41a4-8338-77e50646ccb6"
        }
      ],
      "router": {
        "cases": [
          {
            "arguments": [
              "completed"
            ],
            "category_uuid": "b1da0329-7256-4f03-b738-0d473866fed1",
            "type": "has_only_text",
            "uuid": "c3ad9946-32f3-47b4-ab67-322e18ee01ca"
          },
          {
            "arguments": [
              "expired"
            ],
            "category_uuid": "a3bbef57-1d5e-4603-8e08-af62ca6dcdc7",
            "type": "has_only_text",
            "uuid": "f334864a-5e01-4272-b2f1-d9ac96a2295f"
          }
        ],
        "categories": [
          {
            "exit_uuid": "3b12c3c3-063f-40c7-88b8-f36ba10f7345",
            "name": "Complete",
            "uuid": "b1da0329-7256-4f03-b738-0d473866fed1"
          },
          {
            "exit_uuid": "bd9ab4e3-e189-41a4-8338-77e50646ccb6",
            "name": "Expired",
            "uuid": "a3bbef57-1d5e-4603-8e08-af62ca6dcdc7"
          }
        ],
        "default_category_uuid": "a3bbef57-1d5e-4603-8e08-af62ca6dcdc7",
        "operand": "@child.run.status",
        "type": "switch"
      },
      "uuid": "445bd23e-b901-457e-ada7-2025a126eda6"
    },
    {
      "actions": [
        {
          "flow": {
            "name": "BehaveFlow - problem solving",
            "uuid": "f09d56a4-f6ec-4824-8eda-92a4c527a0c2"
          },
          "type": "enter_flow",
          "uuid": "c70c3926-0608-4484-b312-740694be13c9"
        }
      ],
      "exits": [
        {
          "destination_uuid": "27b563aa-75a5-45a0-930c-43a8796fbcbf",
          "uuid": "f3bac081-cf19-4d91-b14c-b4b301ceaeea"
        },
        {
          "destination_uuid": null,
          "uuid": "e24a6e2b-698e-48ce-bebb-09043b4e11bf"
        }
      ],
      "router": {
        "cases": [
          {
            "arguments": [
              "completed"
            ],
            "category_uuid": "5b321299-33de-4858-a30f-fe5982faf157",
            "type": "has_only_text",
            "uuid": "0e1c486d-78c9-474a-8632-5b8c09b35892"
          },
          {
            "arguments": [
              "expired"
            ],
            "category_uuid": "ad963687-7331-4ea5-a9ff-ae4a08cc155d",
            "type": "has_only_text",
            "uuid": "6aa9f9a1-0636-438c-97d6-937399dff36d"
          }
        ],
        "categories": [
          {
            "exit_uuid": "f3bac081-cf19-4d91-b14c-b4b301ceaeea",
            "name": "Complete",
            "uuid": "5b321299-33de-4858-a30f-fe5982faf157"
          },
          {
            "exit_uuid": "e24a6e2b-698e-48ce-bebb-09043b4e11bf",
            "name": "Expired",
            "uuid": "ad963687-7331-4ea5-a9ff-ae4a08cc155d"
          }
        ],
        "default_category_uuid": "ad963687-7331-4ea5-a9ff-ae4a08cc155d",
        "operand": "@child.run.status",
        "type": "switch"
      },
      "uuid": "d8608c2f-3c89-4fe8-a4af-84ffb923ec61"
    },
    {
      "actions": [
        {
          "flow": {
            "name": "COVIDFlow",
            "uuid": "8c6fb5bf-5f90-4a33-8fdb-ecd3ffd4b906"
          },
          "type": "enter_flow",
          "uuid": "c7b2c080-9606-479e-9c81-f6d5d7d28c64"
        }
      ],
      "exits": [
        {
          "destination_uuid": "27b563aa-75a5-45a0-930c-43a8796fbcbf",
          "uuid": "c9ed000e-c054-445d-b77d-9858f37f35db"
        },
        {
          "destination_uuid": null,
          "uuid": "e44f5353-b502-44ea-9a5b-ba86aa5e20a2"
        }
      ],
      "router": {
        "cases": [
          {
            "arguments": [
              "completed"
            ],
            "category_uuid": "1b669163-9827-4fb9-9411-caddf44deee9",
            "type": "has_only_text",
            "uuid": "bc9bf954-1425-4c80-ad93-2b24fc5b742d"
          },
          {
            "arguments": [
              "expired"
            ],
            "category_uuid": "0da8c20d-1287-4ae1-b2ed-53d9cdccd13a",
            "type": "has_only_text",
            "uuid": "f06e7bc6-b0fa-4ee1-9268-28d0ecb4025a"
          }
        ],
        "categories": [
          {
            "exit_uuid": "c9ed000e-c054-445d-b77d-9858f37f35db",
            "name": "Complete",
            "uuid": "1b669163-9827-4fb9-9411-caddf44deee9"
          },
          {
            "exit_uuid": "e44f5353-b502-44ea-9a5b-ba86aa5e20a2",
            "name": "Expired",
            "uuid": "0da8c20d-1287-4ae1-b2ed-53d9cdccd13a"
          }
        ],
        "default_category_uuid": "0da8c20d-1287-4ae1-b2ed-53d9cdccd13a",
        "operand": "@child.run.status",
        "type": "switch"
      },
      "uuid": "60ede010-5e00-4a6a-b896-d74ac839625c"
    },
    {
      "actions": [
        {
          "flow": {
            "name": "Budget flow",
            "uuid": "7b46af18-d9da-428f-bb8b-2f5e04add8e8"
          },
          "type": "enter_flow",
          "uuid": "587838e3-b06c-42d5-ac71-dfea8bc1dacb"
        }
      ],
      "exits": [
        {
          "destination_uuid": "27b563aa-75a5-45a0-930c-43a8796fbcbf",
          "uuid": "c0821b09-0fa8-42a2-9dfe-068a49030b5c"
        },
        {
          "destination_uuid": null,
          "uuid": "6bf1c2a8-fa91-47b8-b2b4-f0378b575431"
        }
      ],
      "router": {
        "cases": [
          {
            "arguments": [
              "completed"
            ],
            "category_uuid": "d9f04ce7-fb1f-4b61-b653-58503b70d16c",
            "type": "has_only_text",
            "uuid": "96cf330a-059b-4f0f-839d-5373c19c7ff2"
          },
          {
            "arguments": [
              "expired"
            ],
            "category_uuid": "8f20c9dc-44c8-44e7-a41d-f3640f5f7349",
            "type": "has_only_text",
            "uuid": "2367fb86-5353-42d9-8b26-42383a11d802"
          }
        ],
        "categories": [
          {
            "exit_uuid": "c0821b09-0fa8-42a2-9dfe-068a49030b5c",
            "name": "Complete",
            "uuid": "d9f04ce7-fb1f-4b61-b653-58503b70d16c"
          },
          {
            "exit_uuid": "6bf1c2a8-fa91-47b8-b2b4-f0378b575431",
            "name": "Expired",
            "uuid": "8f20c9dc-44c8-44e7-a41d-f3640f5f7349"
          }
        ],
        "default_category_uuid": "8f20c9dc-44c8-44e7-a41d-f3640f5f7349",
        "operand": "@child.run.status",
        "type": "switch"
      },
      "uuid": "57d1db55-6919-46d3-8958-b60301261eec"
    },
    {
      "actions": [],
      "exits": [
        {
          "destination_uuid": "c5f33880-b3b7-40b1-9c8d-1f11ed603ea4",
          "uuid": "411d4e7f-f040-4f1e-a18f-59584a0528a3"
        },
        {
          "destination_uuid": "e99c7604-5d60-4295-9d53-6c3eabc3cb90",
          "uuid": "e2985e46-9381-45b6-a332-6d18ed9bca88"
        },
        {
          "destination_uuid": "e56b17f8-5ed4-4f1c-9852-990fefd704db",
          "uuid": "d4817436-c519-4e1e-a396-6111edcfd490"
        },
        {
          "destination_uuid": "fd5f6732-40f8-44c5-9e70-b1e5593fc3c9",
          "uuid": "cbbfa99c-be60-4f2f-a8d2-fff1dc22a24d"
        },
        {
          "destination_uuid": "828e7627-5cdb-4477-9429-ffae26840966",
          "uuid": "8dc9d699-b9ec-4aaf-97fd-423451d3a652"
        },
        {
          "destination_uuid": "2705691c-e6bd-43ae-980f-2b4109b040cd",
          "uuid": "ccf6a361-8537-495d-8724-3de158c480c8"
        },
        {
          "destination_uuid": "96f73aef-7c35-4302-ab0e-15ae2d1c0ddf",
          "uuid": "e13b2ee4-399a-4693-9ded-000e903e9771"
        },
        {
          "destination_uuid": "f5ec8299-a71b-46d8-a1af-329e1b019d03",
          "uuid": "262b43ad-d77c-4ba1-a12f-39e99bbd14bb"
        },
        {
          "destination_uuid": "edab3dd3-0bf5-464b-b4ec-fcd14f98cc1d",
          "uuid": "43a12f89-0b85-451b-baad-66497aee40c0"
        },
        {
          "destination_uuid": "f2242e16-ef6e-441e-b7e8-8adfbcf7d741",
          "uuid": "4609171b-5831-4598-947f-013cc16504dd"
        },
        {
          "destination_uuid": "6a542ecf-83a0-4db1-b744-3f4e53512cf0",
          "uuid": "4c643327-16fc-49b3-9c36-d283ffdd53a3"
        },
        {
          "destination_uuid": "d8608c2f-3c89-4fe8-a4af-84ffb923ec61",
          "uuid": "276f3dc8-c495-4df7-bb58-e5150a94fab5"
        },
        {
          "destination_uuid": "74261f31-b91b-410a-b96f-8ec8ab1469df",
          "uuid": "82b4446e-2449-4e4c-9ab5-b98b38469acc"
        },
        {
          "destination_uuid": "38b6223a-fd99-4b96-bedd-cf6ec6dcf44b",
          "uuid": "09fe3e46-3262-45cf-9918-9606e05b9ba0"
        },
        {
          "destination_uuid": "150d3ac7-46f5-4325-90cc-dbafbc94caf8",
          "uuid": "0f0c4812-56dc-440b-891a-d6103cc27a76"
        },
        {
          "destination_uuid": "40ce064e-705d-4b2e-84bb-bae338c45509",
          "uuid": "e7b0fd7a-dff3-4b1f-8b5e-24cc418225a7"
        },
        {
          "destination_uuid": "e1382546-aed0-4329-af6c-ccdcd43aba27",
          "uuid": "0d004a1b-b12e-4124-b299-3a1c4c808822"
        },
        {
          "destination_uuid": "ea9cfa3c-84b3-4282-be6e-7b0a15f24aa2",
          "uuid": "78e2ffb7-caa0-4394-963e-0aa825a22c96"
        },
        {
          "destination_uuid": "57d1db55-6919-46d3-8958-b60301261eec",
          "uuid": "6962c270-b2b4-4755-8c4e-89f37c41af5a"
        },
        {
          "destination_uuid": "60ede010-5e00-4a6a-b896-d74ac839625c",
          "uuid": "b0939f7b-fd0c-46de-a6b4-4209dc285b17"
        },
        {
          "destination_uuid": "445bd23e-b901-457e-ada7-2025a126eda6",
          "uuid": "79e389ee-c479-4bf0-9d4e-686a9d0712b1"
        },
        {
          "destination_uuid": "f40feb2f-2b4d-4a82-934a-6ec845662dff",
          "uuid": "ca5e452f-74ee-44d3-a92d-bf8521024e34"
        },
        {
          "destination_uuid": "b9abbfbf-6fc2-4a4b-9d7c-5cafec3aae06",
          "uuid": "981a8928-4c00-43c3-99eb-291fb8d96454"
        },
        {
          "destination_uuid": "b04258f3-405f-4d25-9627-7873147a5f8d",
          "uuid": "7f814b42-e8bf-4eca-a77b-2e059b82b17e"
        },
        {
          "destination_uuid": null,
          "uuid": "2e942989-71a1-4cb0-b8d7-dd51bafac76c"
        }
      ],
      "router": {
        "cases": [
          {
            "arguments": [
              "1"
            ],
            "category_uuid": "79c1237d-5dd3-4303-b038-1b7d8aee25e4",
            "type": "has_number_eq",
            "uuid": "7314875d-8e3b-4feb-a213-f6f3185c30cd"
          },
          {
            "arguments": [
              "2"
            ],
            "category_uuid": "56e29aae-3854-4feb-9218-95d2dbdf256c",
            "type": "has_number_eq",
            "uuid": "a25da804-8303-4420-9729-003b93f33afd"
          },
          {
            "arguments": [
              "3"
            ],
            "category_uuid": "1ae18e14-9a3b-4208-b745-5116c9b9f082",
            "type": "has_number_eq",
            "uuid": "c1876fc8-f540-4607-9ac3-3955fcc19d09"
          },
          {
            "arguments": [
              "4"
            ],
            "category_uuid": "d2b09e1a-3c2b-4536-ac6f-e7935016157a",
            "type": "has_number_eq",
            "uuid": "ece89f93-504d-4870-afbb-221554c6d6ca"
          },
          {
            "arguments": [
              "5"
            ],
            "category_uuid": "c91f509d-8564-4826-afeb-504ed0072541",
            "type": "has_number_eq",
            "uuid": "483522bd-d0a7-44e2-a26d-871807057cfd"
          },
          {
            "arguments": [
              "6"
            ],
            "category_uuid": "9a053dee-9201-4fae-92d2-a74a9d1e3203",
            "type": "has_number_eq",
            "uuid": "0335a726-c59c-431f-94a9-ecf6dac94bd2"
          },
          {
            "arguments": [
              "7"
            ],
            "category_uuid": "b0c50b90-3b89-46e8-bb87-5d27791ebec8",
            "type": "has_number_eq",
            "uuid": "e3844566-bd62-4692-bfe6-da78de403e9b"
          },
          {
            "arguments": [
              "8"
            ],
            "category_uuid": "a962e404-b0fc-4fda-accc-b1930d06cc9b",
            "type": "has_number_eq",
            "uuid": "e0202402-d85d-487a-b5a1-c69566601dff"
          },
          {
            "arguments": [
              "9"
            ],
            "category_uuid": "04a0c31c-f74b-482e-a3f3-705af88f9d0a",
            "type": "has_number_eq",
            "uuid": "1d67652b-7040-4307-991d-aa67b21bf4af"
          },
          {
            "arguments": [
              "10"
            ],
            "category_uuid": "dbc225cc-1bb9-4140-a44d-a4874fb9c17f",
            "type": "has_number_eq",
            "uuid": "12a83484-bc51-4314-8651-c1c3fbd86f70"
          },
          {
            "arguments": [
              "11"
            ],
            "category_uuid": "f9812c86-1ffe-4349-bb8d-8a499917d7dc",
            "type": "has_number_eq",
            "uuid": "5551a8e9-ec84-46ee-8a7a-97a62d48e34e"
          },
          {
            "arguments": [
              "12"
            ],
            "category_uuid": "2e4c2c55-faf8-49bd-ab4f-ef7dd969a7c3",
            "type": "has_number_eq",
            "uuid": "f580cdec-deb2-4319-8c1a-089a9f1f6ad6"
          },
          {
            "arguments": [
              "13"
            ],
            "category_uuid": "81b1521b-195c-4e64-a4eb-536d18ee32b0",
            "type": "has_number_eq",
            "uuid": "69850170-0985-4afa-b9c4-324413473248"
          },
          {
            "arguments": [
              "14"
            ],
            "category_uuid": "a20ae797-2975-469c-a687-65af662cde68",
            "type": "has_number_eq",
            "uuid": "61d1dc9e-8fa9-4745-a234-27af42812a6f"
          },
          {
            "arguments": [
              "15"
            ],
            "category_uuid": "5bf040f7-7e60-4d9f-b72d-9444b10bd875",
            "type": "has_number_eq",
            "uuid": "707e0bca-288a-4aa9-8992-22a4a7b184a7"
          },
          {
            "arguments": [
              "16"
            ],
            "category_uuid": "37b585fe-f624-4423-a495-d73e74cd3b77",
            "type": "has_number_eq",
            "uuid": "05d5ac67-af81-45de-b320-ffef35d4d3a8"
          },
          {
            "arguments": [
              "17"
            ],
            "category_uuid": "11b73ad9-b16d-4eeb-acdd-a4c1bf9de8b0",
            "type": "has_number_eq",
            "uuid": "f11eba36-ab90-49d0-925a-281a260eb409"
          },
          {
            "arguments": [
              "18"
            ],
            "category_uuid": "c5190dc5-41ae-49d5-9dce-69e1d5a92a7d",
            "type": "has_number_eq",
            "uuid": "d8d45a73-a032-4066-8eff-373ce0464883"
          },
          {
            "arguments": [
              "19"
            ],
            "category_uuid": "3180fee0-91f0-4b85-b76b-1bdc7638ba69",
            "type": "has_number_eq",
            "uuid": "f591ad62-5873-473b-ab81-0a34ce48ef2f"
          },
          {
            "arguments": [
              "20"
            ],
            "category_uuid": "4d95fcaf-5766-4f7d-bb90-19ca55b5b76c",
            "type": "has_number_eq",
            "uuid": "92fa8cf2-0e5b-45c5-85cb-63f25069e2f3"
          },
          {
            "arguments": [
              "21"
            ],
            "category_uuid": "be22140f-f04d-43c5-b235-fc3f605f89a9",
            "type": "has_number_eq",
            "uuid": "42f9031e-7224-47d0-842b-7c3149f557a1"
          },
          {
            "arguments": [
              "22"
            ],
            "category_uuid": "4eb4bad5-50e6-4ebc-8c2a-6d40ade9b151",
            "type": "has_number_eq",
            "uuid": "ae6d557e-1d35-4df7-b399-044dcb42642b"
          },
          {
            "arguments": [
              "23"
            ],
            "category_uuid": "c57f2dc0-c26a-47fc-acce-e705c52e4224",
            "type": "has_number_eq",
            "uuid": "0affbd2f-03c3-4137-b281-1dc734e5f983"
          },
          {
            "arguments": [
              "24"
            ],
            "category_uuid": "65b8e137-c596-45b3-a46f-860bd7736a8d",
            "type": "has_number_eq",
            "uuid": "77bb6d9c-6ca7-4f5c-8aac-c6fab50279ae"
          }
        ],
        "categories": [
          {
            "exit_uuid": "411d4e7f-f040-4f1e-a18f-59584a0528a3",
            "name": "1",
            "uuid": "79c1237d-5dd3-4303-b038-1b7d8aee25e4"
          },
          {
            "exit_uuid": "e2985e46-9381-45b6-a332-6d18ed9bca88",
            "name": "2",
            "uuid": "56e29aae-3854-4feb-9218-95d2dbdf256c"
          },
          {
            "exit_uuid": "d4817436-c519-4e1e-a396-6111edcfd490",
            "name": "3",
            "uuid": "1ae18e14-9a3b-4208-b745-5116c9b9f082"
          },
          {
            "exit_uuid": "cbbfa99c-be60-4f2f-a8d2-fff1dc22a24d",
            "name": "4",
            "uuid": "d2b09e1a-3c2b-4536-ac6f-e7935016157a"
          },
          {
            "exit_uuid": "8dc9d699-b9ec-4aaf-97fd-423451d3a652",
            "name": "5",
            "uuid": "c91f509d-8564-4826-afeb-504ed0072541"
          },
          {
            "exit_uuid": "ccf6a361-8537-495d-8724-3de158c480c8",
            "name": "6",
            "uuid": "9a053dee-9201-4fae-92d2-a74a9d1e3203"
          },
          {
            "exit_uuid": "e13b2ee4-399a-4693-9ded-000e903e9771",
            "name": "7",
            "uuid": "b0c50b90-3b89-46e8-bb87-5d27791ebec8"
          },
          {
            "exit_uuid": "262b43ad-d77c-4ba1-a12f-39e99bbd14bb",
            "name": "8",
            "uuid": "a962e404-b0fc-4fda-accc-b1930d06cc9b"
          },
          {
            "exit_uuid": "43a12f89-0b85-451b-baad-66497aee40c0",
            "name": "9",
            "uuid": "04a0c31c-f74b-482e-a3f3-705af88f9d0a"
          },
          {
            "exit_uuid": "4609171b-5831-4598-947f-013cc16504dd",
            "name": "10",
            "uuid": "dbc225cc-1bb9-4140-a44d-a4874fb9c17f"
          },
          {
            "exit_uuid": "4c643327-16fc-49b3-9c36-d283ffdd53a3",
            "name": "11",
            "uuid": "f9812c86-1ffe-4349-bb8d-8a499917d7dc"
          },
          {
            "exit_uuid": "276f3dc8-c495-4df7-bb58-e5150a94fab5",
            "name": "12",
            "uuid": "2e4c2c55-faf8-49bd-ab4f-ef7dd969a7c3"
          },
          {
            "exit_uuid": "82b4446e-2449-4e4c-9ab5-b98b38469acc",
            "name": "13",
            "uuid": "81b1521b-195c-4e64-a4eb-536d18ee32b0"
          },
          {
            "exit_uuid": "09fe3e46-3262-45cf-9918-9606e05b9ba0",
            "name": "14",
            "uuid": "a20ae797-2975-469c-a687-65af662cde68"
          },
          {
            "exit_uuid": "0f0c4812-56dc-440b-891a-d6103cc27a76",
            "name": "15",
            "uuid": "5bf040f7-7e60-4d9f-b72d-9444b10bd875"
          },
          {
            "exit_uuid": "e7b0fd7a-dff3-4b1f-8b5e-24cc418225a7",
            "name": "16",
            "uuid": "37b585fe-f624-4423-a495-d73e74cd3b77"
          },
          {
            "exit_uuid": "0d004a1b-b12e-4124-b299-3a1c4c808822",
            "name": "17",
            "uuid": "11b73ad9-b16d-4eeb-acdd-a4c1bf9de8b0"
          },
          {
            "exit_uuid": "78e2ffb7-caa0-4394-963e-0aa825a22c96",
            "name": "18",
            "uuid": "c5190dc5-41ae-49d5-9dce-69e1d5a92a7d"
          },
          {
            "exit_uuid": "6962c270-b2b4-4755-8c4e-89f37c41af5a",
            "name": "19",
            "uuid": "3180fee0-91f0-4b85-b76b-1bdc7638ba69"
          },
          {
            "exit_uuid": "b0939f7b-fd0c-46de-a6b4-4209dc285b17",
            "name": "20",
            "uuid": "4d95fcaf-5766-4f7d-bb90-19ca55b5b76c"
          },
          {
            "exit_uuid": "79e389ee-c479-4bf0-9d4e-686a9d0712b1",
            "name": "21",
            "uuid": "be22140f-f04d-43c5-b235-fc3f605f89a9"
          },
          {
            "exit_uuid": "ca5e452f-74ee-44d3-a92d-bf8521024e34",
            "name": "22",
            "uuid": "4eb4bad5-50e6-4ebc-8c2a-6d40ade9b151"
          },
          {
            "exit_uuid": "981a8928-4c00-43c3-99eb-291fb8d96454",
            "name": "23",
            "uuid": "c57f2dc0-c26a-47fc-acce-e705c52e4224"
          },
          {
            "exit_uuid": "7f814b42-e8bf-4eca-a77b-2e059b82b17e",
            "name": "24",
            "uuid": "65b8e137-c596-45b3-a46f-860bd7736a8d"
          },
          {
            "exit_uuid": "2e942989-71a1-4cb0-b8d7-dd51bafac76c",
            "name": "Other",
            "uuid": "47c04ab2-80ad-407f-9c1b-98219c5a4a98"
          }
        ],
        "default_category_uuid": "47c04ab2-80ad-407f-9c1b-98219c5a4a98",
        "operand": "@results.index_of_skill",
        "type": "switch"
      },
      "uuid": "b687cf52-17cc-47a1-b5a9-22d690ec7072"
    },
    {
      "actions": [
        {
          "all_urns": false,
          "attachments": [],
          "quick_replies": [
            "Yes",
            "No"
          ],
          "text": "Would you like to go back to the Help menu?",
          "type": "send_msg",
          "uuid": "adc3ebc9-8e32-4e3e-a2ad-775ef48acde7"
        }
      ],
      "exits": [
        {
          "destination_uuid": "817c059a-b5f3-46c8-b184-10ea3223c418",
          "uuid": "8c2fb9e4-6f8b-433a-a31c-97eb53cb19ec"
        }
      ],
      "uuid": "27b563aa-75a5-45a0-930c-43a8796fbcbf"
    },
    {
      "actions": [],
      "exits": [
        {
          "destination_uuid": "6ab88684-82fc-4ad3-9568-c0bc5112c355",
          "uuid": "c429a537-1944-4107-bf73-f0316e0d7219"
        },
        {
          "uuid": "9e66b1c8-96be-480f-8b9c-31f48629784d"
        },
        {
          "destination_uuid": "0af05335-7e24-425e-a7f1-e66e8d1621eb",
          "uuid": "f9b71dac-5627-4621-93b0-4c5608f34665"
        }
      ],
      "router": {
        "cases": [
          {
            "arguments": [
              "yes y back"
            ],
            "category_uuid": "1ceabb73-966b-458a-a4cc-f789489bff8c",
            "type": "has_any_word",
            "uuid": "fd8bc39c-965d-4b84-b36f-6ac939facea8"
          },
          {
            "arguments": [
              "no n"
            ],
            "category_uuid": "443d744a-0482-482b-a8ab-88d993f98afa",
            "type": "has_any_word",
            "uuid": "eaae651c-e6e1-474e-8ab7-590b940db69b"
          }
        ],
        "categories": [
          {
            "exit_uuid": "c429a537-1944-4107-bf73-f0316e0d7219",
            "name": "Yes",
            "uuid": "1ceabb73-966b-458a-a4cc-f789489bff8c"
          },
          {
            "exit_uuid": "9e66b1c8-96be-480f-8b9c-31f48629784d",
            "name": "No",
            "uuid": "443d744a-0482-482b-a8ab-88d993f98afa"
          },
          {
            "exit_uuid": "f9b71dac-5627-4621-93b0-4c5608f34665",
            "name": "Other",
            "uuid": "a4f2778b-fc14-41ae-bff5-f96fc4eb47c1"
          }
        ],
        "default_category_uuid": "a4f2778b-fc14-41ae-bff5-f96fc4eb47c1",
        "operand": "@input.text",
        "result_name": "Result 5",
        "type": "switch",
        "wait": {
          "type": "msg"
        }
      },
      "uuid": "817c059a-b5f3-46c8-b184-10ea3223c418"
    },
    {
      "actions": [
        {
          "attachments": [],
          "quick_replies": [],
          "text": "Sorry, I don't understand what you mean.",
          "type": "send_msg",
          "uuid": "deba3ab6-5163-48f5-8afb-c1f4e8f8f4dc"
        }
      ],
      "exits": [
        {
          "destination_uuid": "27b563aa-75a5-45a0-930c-43a8796fbcbf",
          "uuid": "6cad04a5-bedc-4191-8e60-37197ac9db63"
        }
      ],
      "uuid": "0af05335-7e24-425e-a7f1-e66e8d1621eb"
    },
    {
      "actions": [
        {
          "flow": {
            "name": "PLH - Help - Entry",
            "uuid": "3aad1291-ad9a-4a18-bb99-d5357e49345b"
          },
          "type": "enter_flow",
          "uuid": "16477cad-aa59-4a27-8f14-f6958ce102ba"
        }
      ],
      "exits": [
        {
          "destination_uuid": null,
          "uuid": "45c4d2ff-73b6-41d5-9080-afc7b974c03a"
        },
        {
          "destination_uuid": null,
          "uuid": "67cbafb9-371c-4113-ac63-cf0d1ad36947"
        }
      ],
      "router": {
        "cases": [
          {
            "arguments": [
              "completed"
            ],
            "category_uuid": "abfffd92-9182-4962-8bcf-66cd50c997d8",
            "type": "has_only_text",
            "uuid": "dd969991-d966-45e3-b64e-c14a8d0a10d8"
          },
          {
            "arguments": [
              "expired"
            ],
            "category_uuid": "6bf0382f-0c3c-436d-af37-5d50493fd554",
            "type": "has_only_text",
            "uuid": "5fe8f724-c96e-42e8-87ca-58f5ee297164"
          }
        ],
        "categories": [
          {
            "exit_uuid": "45c4d2ff-73b6-41d5-9080-afc7b974c03a",
            "name": "Complete",
            "uuid": "abfffd92-9182-4962-8bcf-66cd50c997d8"
          },
          {
            "exit_uuid": "67cbafb9-371c-4113-ac63-cf0d1ad36947",
            "name": "Expired",
            "uuid": "6bf0382f-0c3c-436d-af37-5d50493fd554"
          }
        ],
        "default_category_uuid": "6bf0382f-0c3c-436d-af37-5d50493fd554",
        "operand": "@child.run.status",
        "type": "switch"
      },
      "uuid": "6ab88684-82fc-4ad3-9568-c0bc5112c355"
    }
  ],
  "spec_version": "13.1.0",
  "type": "messaging",
  "uuid": "ddc9840d-140f-494d-bd3e-9617183ba7ee",
  "revision": 1
}